<!--Copyright 2018 MLB Advanced Media, L.P.  Use of any content on this page acknowledges agreement to the terms posted here http://gdx.mlb.com/components/copyright.txt--><game atBat="506560" deck="595222" hole="642727" ind="FT"><inning num="1" away_team="nyn" home_team="det" next="Y"><top><atbat num="1" b="0" s="3" o="1" start_tfs="180658" start_tfs_zulu="2018-03-09T18:06:58Z" end_tfs_zulu="2018-03-09T18:08:52Z" batter="501571" stand="R" b_height="6-1" pitcher="605242" p_throws="R" des="Juan Lagares strikes out swinging.  " des_es="Juan Lagares se poncha tir&#225;ndole.  " event_num="7" event="Strikeout" event_es="Ponche" home_team_runs="0" away_team_runs="0"><pitch des="Called Strike" des_es="Strike cantado" id="3" type="S" code="C" tfs="180816" tfs_zulu="2018-03-09T18:08:16Z" x="118.95282055311125" y="159.87246621621628" event_num="3" sz_top="3.411" sz_bot="1.565"  cc="" mt=""/><pitch des="Called Strike" des_es="Strike cantado" id="4" type="S" code="C" tfs="180846" tfs_zulu="2018-03-09T18:08:46Z" x="118.95282055311125" y="123.80722128378383" event_num="4" sz_top="3.411" sz_bot="1.565"  cc="" mt=""/><pitch des="Swinging Strike" des_es="Strike tir&#225;ndole" id="5" type="S" code="S" tfs="180851" tfs_zulu="2018-03-09T18:08:51Z" x="128.61950031426775" y="189.82495777027034" event_num="5" sz_top="3.411" sz_bot="1.565"  cc="" mt=""/></atbat><atbat num="2" b="0" s="0" o="2" start_tfs="180853" start_tfs_zulu="2018-03-09T18:08:53Z" end_tfs_zulu="2018-03-09T18:09:40Z" batter="408314" stand="L" b_height="6-0" pitcher="605242" p_throws="R" des="Jose Reyes grounds out, first baseman Miguel Cabrera to pitcher Michael Fulmer.  " des_es="Jose Reyes batea rodado de out, primera base Miguel Cabrera a lanzador Michael Fulmer.  " event_num="11" event="Groundout" event_es="Roletazo de Out" home_team_runs="0" away_team_runs="0"><pitch des="In play, out(s)" des_es="En juego, out(s)" id="9" type="X" code="X" tfs="180929" tfs_zulu="2018-03-09T18:09:29Z" x="104.16848680075424" y="157.42736486486493" event_num="9" sz_top="3.371" sz_bot="1.535"  cc="" mt=""/></atbat><atbat num="3" b="0" s="0" o="2" start_tfs="180942" start_tfs_zulu="2018-03-09T18:09:42Z" end_tfs_zulu="2018-03-09T18:11:04Z" batter="453943" stand="R" b_height="6-3" pitcher="605242" p_throws="R" des="Todd Frazier singles on a ground ball to left fielder JaCoby Jones.  " des_es="Todd Frazier pega sencillo con rodado a jardinero izquierdo JaCoby Jones.  " event_num="15" event="Single" event_es="Sencillo" home_team_runs="0" away_team_runs="0"><pitch des="In play, no out" des_es="En juego, no out" id="13" type="X" code="D" tfs="181052" tfs_zulu="2018-03-09T18:10:52Z" x="108.71751257071024" y="158.64991554054063" event_num="13" sz_top="3.49" sz_bot="1.601"  cc="" mt=""/><runner id="453943" start="" end="1B" event="Single" event_num="15"/></atbat><atbat num="4" b="0" s="3" o="3" start_tfs="181134" start_tfs_zulu="2018-03-09T18:11:34Z" end_tfs_zulu="2018-03-09T18:12:33Z" batter="527038" stand="R" b_height="6-3" pitcher="605242" p_throws="R" des="Wilmer Flores strikes out swinging.  " des_es="Wilmer Flores se poncha tir&#225;ndole.  " event_num="21" event="Strikeout" event_es="Ponche" home_team_runs="0" away_team_runs="0"><pitch des="Swinging Strike" des_es="Strike tir&#225;ndole" id="17" type="S" code="S" tfs="181220" tfs_zulu="2018-03-09T18:12:20Z" x="112.69791011942173" y="117.08319256756761" event_num="17" on_1b="453943" sz_top="3.49" sz_bot="1.601"  cc="" mt=""/><pitch des="Foul" des_es="Foul" id="18" type="S" code="F" tfs="181225" tfs_zulu="2018-03-09T18:12:25Z" x="103.03123035826523" y="165.98521959459467" event_num="18" on_1b="453943" sz_top="3.49" sz_bot="1.601"  cc="" mt=""/><pitch des="Swinging Strike" des_es="Strike tir&#225;ndole" id="19" type="S" code="S" tfs="181231" tfs_zulu="2018-03-09T18:12:31Z" x="95.63906348208674" y="155.5935388513514" event_num="19" on_1b="453943" sz_top="3.49" sz_bot="1.601"  cc="" mt=""/><runner id="453943" start="1B" end="" event="Strikeout" event_num="21"/></atbat></top><bottom><atbat num="5" b="0" s="0" o="0" start_tfs="181402" start_tfs_zulu="2018-03-09T18:14:02Z" end_tfs_zulu="2018-03-09T18:16:12Z" batter="547982" stand="L" b_height="6-2" pitcher="571927" p_throws="L" des="Leonys Martin doubles (1) on a sharp line drive to right fielder Matthew den Dekker.  " des_es="Leonys Martin pega doble (1) con l&#237;nea fuerte a jardinero derecho Matthew den Dekker.  " event_num="27" event="Double" event_es="Doble" home_team_runs="0" away_team_runs="0"><pitch des="In play, no out" des_es="En juego, no out" id="25" type="X" code="D" tfs="181559" tfs_zulu="2018-03-09T18:15:59Z" x="97.34494814582024" y="131.1425253378379" event_num="25" sz_top="3.467" sz_bot="1.589"  cc="" mt=""/><runner id="547982" start="" end="2B" event="Double" event_num="27"/></atbat><atbat num="6" b="0" s="0" o="1" start_tfs="181616" start_tfs_zulu="2018-03-09T18:16:16Z" end_tfs_zulu="2018-03-09T18:18:10Z" batter="578428" stand="R" b_height="5-11" pitcher="571927" p_throws="L" des="Jose Iglesias grounds out softly, third baseman Todd Frazier to first baseman Wilmer Flores.  " des_es="Jose Iglesias batea rodado de out suavemente, tercera base Todd Frazier a primera base Wilmer Flores.  " event_num="31" event="Groundout" event_es="Roletazo de Out" home_team_runs="0" away_team_runs="0"><pitch des="In play, out(s)" des_es="En juego, out(s)" id="29" type="X" code="X" tfs="181754" tfs_zulu="2018-03-09T18:17:54Z" x="117.24693588937774" y="161.09501689189193" event_num="29" on_2b="547982" sz_top="3.319" sz_bot="1.513"  cc="" mt=""/></atbat><action b="0" s="0" o="2" des="With Miguel Cabrera batting, Leonys Martin caught stealing 3rd base, pitcher Steven Matz to third baseman Todd Frazier.  " des_es="Con Miguel Cabrera bateando, Leonys Martin atrapado robando la 3ra base, lanzador Steven Matz a tercera base Todd Frazier.  " event="Caught Stealing 3B" event_es="Retirado en Intento de Robo 3B" tfs="181913" tfs_zulu="2018-03-09T18:19:13Z" player="547982" pitch="0" event_num="35" home_team_runs="0" away_team_runs="0"/><atbat num="7" b="0" s="3" o="3" start_tfs="181812" start_tfs_zulu="2018-03-09T18:18:12Z" end_tfs_zulu="2018-03-09T18:20:38Z" batter="408234" stand="R" b_height="6-4" pitcher="571927" p_throws="L" des="Miguel Cabrera called out on strikes.  " des_es="Miguel Cabrera se poncha sin tirarle.  " event_num="40" event="Strikeout" event_es="Ponche" home_team_runs="0" away_team_runs="0"><runner id="547982" start="2B" end="" event="Caught Stealing 3B" event_num="35"/><pitch des="Called Strike" des_es="Strike cantado" id="36" type="S" code="C" tfs="182031" tfs_zulu="2018-03-09T18:20:31Z" x="105.87437146448774" y="127.47487331081085" event_num="36" sz_top="3.549" sz_bot="1.627"  cc="" mt=""/><pitch des="Swinging Strike" des_es="Strike tir&#225;ndole" id="37" type="S" code="S" tfs="182033" tfs_zulu="2018-03-09T18:20:33Z" x="107.58025612822125" y="154.98226351351357" event_num="37" sz_top="3.549" sz_bot="1.627"  cc="" mt=""/><pitch des="Called Strike" des_es="Strike cantado" id="38" type="S" code="C" tfs="182037" tfs_zulu="2018-03-09T18:20:37Z" x="105.30574324324323" y="168.430320945946" event_num="38" sz_top="3.549" sz_bot="1.627"  cc="" mt=""/></atbat></bottom></inning><inning num="2" away_team="nyn" home_team="det" next="Y"><top><atbat num="8" b="0" s="1" o="0" start_tfs="182215" start_tfs_zulu="2018-03-09T18:22:15Z" end_tfs_zulu="2018-03-09T18:23:33Z" batter="608700" stand="R" b_height="6-2" pitcher="605242" p_throws="R" des="Kevin Plawecki homers (1) on a fly ball to left field.  " des_es="Kevin Plawecki batea jonr&#243;n (1) con elevado por el jard&#237;n izquierdo.  " event_num="47" event="Home Run" event_es="Jonr&#243;n" score="T" home_team_runs="0" away_team_runs="1"><pitch des="Called Strike" des_es="Strike cantado" id="43" type="S" code="C" tfs="182318" tfs_zulu="2018-03-09T18:23:18Z" x="120.09007699560024" y="155.5935388513514" event_num="43" sz_top="3.467" sz_bot="1.589"  cc="" mt=""/><pitch des="In play, run(s)" des_es="En juego, carrera(s)" id="44" type="X" code="E" tfs="182325" tfs_zulu="2018-03-09T18:23:25Z" x="120.09007699560024" y="109.13661317567573" event_num="44" sz_top="3.467" sz_bot="1.589"  cc="" mt=""/><runner id="608700" start="" end="" event="Home Run" event_num="47" score="T" rbi="T" earned="T"/></atbat><atbat num="9" b="0" s="0" o="0" start_tfs="182334" start_tfs_zulu="2018-03-09T18:23:34Z" end_tfs_zulu="2018-03-09T18:25:25Z" batter="446653" stand="L" b_height="6-1" pitcher="605242" p_throws="R" des="Jose Lobaton doubles (1) on a fly ball to right fielder Nicholas Castellanos.  " des_es="Jose Lobaton pega doble (1) con elevado a jardinero derecho Nicholas Castellanos.  " event_num="51" event="Double" event_es="Doble" home_team_runs="0" away_team_runs="1"><pitch des="In play, no out" des_es="En juego, no out" id="49" type="X" code="D" tfs="182515" tfs_zulu="2018-03-09T18:25:15Z" x="102.46260213702072" y="122.58467060810815" event_num="49" sz_top="3.411" sz_bot="1.565"  cc="" mt=""/><runner id="446653" start="" end="2B" event="Double" event_num="51"/></atbat><atbat num="10" b="0" s="0" o="1" start_tfs="182623" start_tfs_zulu="2018-03-09T18:26:23Z" end_tfs_zulu="2018-03-09T18:26:57Z" batter="608325" stand="R" b_height="6-2" pitcher="605242" p_throws="R" des="Gavin Cecchini grounds out, third baseman Jeimer Candelario to first baseman Miguel Cabrera.  " des_es="Gavin Cecchini batea rodado de out, tercera base Jeimer Candelario a primera base Miguel Cabrera.  " event_num="55" event="Groundout" event_es="Roletazo de Out" home_team_runs="0" away_team_runs="1"><pitch des="In play, out(s)" des_es="En juego, out(s)" id="53" type="X" code="X" tfs="182643" tfs_zulu="2018-03-09T18:26:43Z" x="106.44299968573225" y="153.14843750000003" event_num="53" on_2b="446653" sz_top="3.467" sz_bot="1.589"  cc="" mt=""/></atbat><atbat num="11" b="0" s="3" o="2" start_tfs="182729" start_tfs_zulu="2018-03-09T18:27:29Z" end_tfs_zulu="2018-03-09T18:29:10Z" batter="544925" stand="L" b_height="6-2" pitcher="605242" p_throws="R" des="Matthew den Dekker called out on strikes.  " des_es="Matthew den Dekker se poncha sin tirarle.  " event_num="61" event="Strikeout" event_es="Ponche" home_team_runs="0" away_team_runs="1"><pitch des="Foul" des_es="Foul" id="57" type="S" code="F" tfs="182901" tfs_zulu="2018-03-09T18:29:01Z" x="112.12928189817724" y="125.64104729729736" event_num="57" on_2b="446653" sz_top="3.467" sz_bot="1.589"  cc="" mt=""/><pitch des="Called Strike" des_es="Strike cantado" id="58" type="S" code="C" tfs="182904" tfs_zulu="2018-03-09T18:29:04Z" x="95.07043526084225" y="154.98226351351357" event_num="58" on_2b="446653" sz_top="3.467" sz_bot="1.589"  cc="" mt=""/><pitch des="Called Strike" des_es="Strike cantado" id="59" type="S" code="C" tfs="182908" tfs_zulu="2018-03-09T18:29:08Z" x="118.95282055311125" y="167.20777027027032" event_num="59" on_2b="446653" sz_top="3.467" sz_bot="1.589"  cc="" mt=""/></atbat><atbat num="12" b="0" s="3" o="3" start_tfs="183010" start_tfs_zulu="2018-03-09T18:30:10Z" end_tfs_zulu="2018-03-09T18:31:39Z" batter="571841" stand="L" b_height="6-0" pitcher="605242" p_throws="R" des="Ty Kelly called out on strikes.  " des_es="Ty Kelly se poncha sin tirarle.  " event_num="67" event="Strikeout" event_es="Ponche" home_team_runs="0" away_team_runs="1"><pitch des="Foul" des_es="Foul" id="63" type="S" code="F" tfs="183131" tfs_zulu="2018-03-09T18:31:31Z" x="105.87437146448774" y="132.97635135135138" event_num="63" on_2b="446653" sz_top="3.371" sz_bot="1.535"  cc="" mt=""/><pitch des="Foul" des_es="Foul" id="64" type="S" code="F" tfs="183134" tfs_zulu="2018-03-09T18:31:34Z" x="93.93317881835323" y="153.14843750000003" event_num="64" on_2b="446653" sz_top="3.371" sz_bot="1.535"  cc="" mt=""/><pitch des="Called Strike" des_es="Strike cantado" id="65" type="S" code="C" tfs="183137" tfs_zulu="2018-03-09T18:31:37Z" x="121.79596165933374" y="167.20777027027032" event_num="65" on_2b="446653" sz_top="3.371" sz_bot="1.535"  cc="" mt=""/><runner id="446653" start="2B" end="" event="Strikeout" event_num="67"/></atbat></top><bottom><atbat num="13" b="0" s="0" o="0" start_tfs="183314" start_tfs_zulu="2018-03-09T18:33:14Z" end_tfs_zulu="2018-03-09T18:35:16Z" batter="592206" stand="R" b_height="6-4" pitcher="571927" p_throws="L" des="Nicholas Castellanos singles on a ground ball to center fielder Juan Lagares.  " des_es="Nicholas Castellanos pega sencillo con rodado a jardinero central Juan Lagares.  " event_num="73" event="Single" event_es="Sencillo" home_team_runs="0" away_team_runs="1"><pitch des="In play, no out" des_es="En juego, no out" id="71" type="X" code="D" tfs="183505" tfs_zulu="2018-03-09T18:35:05Z" x="100.18808925204273" y="131.1425253378379" event_num="71" sz_top="3.549" sz_bot="1.627"  cc="" mt=""/><runner id="592206" start="" end="1B" event="Single" event_num="73"/></atbat><atbat num="14" b="0" s="0" o="1" start_tfs="183517" start_tfs_zulu="2018-03-09T18:35:17Z" end_tfs_zulu="2018-03-09T18:36:50Z" batter="400121" stand="R" b_height="6-2" pitcher="571927" p_throws="L" des="Victor Martinez flies out to left fielder Ty Kelly.  " des_es="Victor Martinez batea elevado de out a jardinero izquierdo Ty Kelly.  " event_num="77" event="Flyout" event_es="Elevado de Out" home_team_runs="0" away_team_runs="1"><pitch des="In play, out(s)" des_es="En juego, out(s)" id="75" type="X" code="X" tfs="183636" tfs_zulu="2018-03-09T18:36:36Z" x="114.40379478315523" y="121.3621199324325" event_num="75" on_1b="592206" sz_top="3.467" sz_bot="1.589"  cc="" mt=""/></atbat><atbat num="15" b="0" s="0" o="3" start_tfs="183702" start_tfs_zulu="2018-03-09T18:37:02Z" end_tfs_zulu="2018-03-09T18:39:23Z" batter="543510" stand="R" b_height="6-3" pitcher="571927" p_throws="L" des="James McCann grounds into a double play, third baseman Todd Frazier to second baseman Gavin Cecchini to first baseman Wilmer Flores.   Nicholas Castellanos out at 2nd.  " des_es="James McCann batea rodado batea para doble matanza, tercera base Todd Frazier a segunda base Gavin Cecchini a primera base Wilmer Flores.   Nicholas Castellanos a cabo a 2da.  " event_num="82" event="Grounded Into DP" event_es="Roletazo de Doble Play" home_team_runs="0" away_team_runs="1"><pitch des="In play, out(s)" des_es="En juego, out(s)" id="79" type="X" code="X" tfs="183912" tfs_zulu="2018-03-09T18:39:12Z" x="113.83516656191074" y="161.09501689189193" event_num="79" on_1b="592206" sz_top="3.49" sz_bot="1.601"  cc="" mt=""/><runner id="592206" start="1B" end="" event="Grounded Into DP" event_num="82"/></atbat></bottom></inning><inning num="3" away_team="nyn" home_team="det" next="Y"><top><atbat num="16" b="0" s="0" o="1" start_tfs="184117" start_tfs_zulu="2018-03-09T18:41:17Z" end_tfs_zulu="2018-03-09T18:42:41Z" batter="501571" stand="R" b_height="6-1" pitcher="605242" p_throws="R" des="Juan Lagares grounds out sharply, third baseman Jeimer Candelario to first baseman Miguel Cabrera.  " des_es="Juan Lagares batea rodado de out fuertemente, tercera base Jeimer Candelario a primera base Miguel Cabrera.  " event_num="87" event="Groundout" event_es="Roletazo de Out" home_team_runs="0" away_team_runs="1"><pitch des="In play, out(s)" des_es="En juego, out(s)" id="85" type="X" code="X" tfs="184230" tfs_zulu="2018-03-09T18:42:30Z" x="109.28614079195475" y="164.15139358108115" event_num="85" sz_top="3.411" sz_bot="1.565"  cc="" mt=""/></atbat><atbat num="17" b="0" s="0" o="2" start_tfs="184243" start_tfs_zulu="2018-03-09T18:42:43Z" end_tfs_zulu="2018-03-09T18:45:01Z" batter="408314" stand="L" b_height="6-0" pitcher="605242" p_throws="R" des="Jose Reyes grounds out softly, second baseman Dixon Machado to first baseman Miguel Cabrera.  " des_es="Jose Reyes batea rodado de out suavemente, segunda base Dixon Machado a primera base Miguel Cabrera.  " event_num="91" event="Groundout" event_es="Roletazo de Out" home_team_runs="0" away_team_runs="1"><pitch des="In play, out(s)" des_es="En juego, out(s)" id="89" type="X" code="X" tfs="184450" tfs_zulu="2018-03-09T18:44:50Z" x="99.05083280955374" y="157.42736486486493" event_num="89" sz_top="3.371" sz_bot="1.535"  cc="" mt=""/></atbat><atbat num="18" b="0" s="3" o="3" start_tfs="184502" start_tfs_zulu="2018-03-09T18:45:02Z" end_tfs_zulu="2018-03-09T18:46:55Z" batter="453943" stand="R" b_height="6-3" pitcher="605242" p_throws="R" des="Todd Frazier called out on strikes.  " des_es="Todd Frazier se poncha sin tirarle.  " event_num="97" event="Strikeout" event_es="Ponche" home_team_runs="0" away_team_runs="1"><pitch des="Foul" des_es="Foul" id="93" type="S" code="F" tfs="184647" tfs_zulu="2018-03-09T18:46:47Z" x="99.61946103079823" y="129.91997466216222" event_num="93" sz_top="3.49" sz_bot="1.601"  cc="" mt=""/><pitch des="Swinging Strike" des_es="Strike tir&#225;ndole" id="94" type="S" code="S" tfs="184651" tfs_zulu="2018-03-09T18:46:51Z" x="101.89397391577623" y="165.98521959459467" event_num="94" sz_top="3.49" sz_bot="1.601"  cc="" mt=""/><pitch des="Called Strike" des_es="Strike cantado" id="95" type="S" code="C" tfs="184654" tfs_zulu="2018-03-09T18:46:54Z" x="101.32534569453173" y="145.813133445946" event_num="95" sz_top="3.49" sz_bot="1.601"  cc="" mt=""/></atbat></top><bottom><atbat num="19" b="0" s="0" o="1" start_tfs="184828" start_tfs_zulu="2018-03-09T18:48:28Z" end_tfs_zulu="2018-03-09T18:50:30Z" batter="600869" stand="R" b_height="6-1" pitcher="571927" p_throws="L" des="Jeimer Candelario flies out softly to center fielder Juan Lagares.  " des_es="Jeimer Candelario batea elevado de out suavemente a jardinero central Juan Lagares.  " event_num="102" event="Flyout" event_es="Elevado de Out" home_team_runs="0" away_team_runs="1"><pitch des="In play, out(s)" des_es="En juego, out(s)" id="100" type="X" code="X" tfs="185015" tfs_zulu="2018-03-09T18:50:15Z" x="100.75671747328724" y="154.37098817567573" event_num="100" sz_top="3.411" sz_bot="1.565"  cc="" mt=""/></atbat><atbat num="20" b="0" s="0" o="2" start_tfs="185032" start_tfs_zulu="2018-03-09T18:50:32Z" end_tfs_zulu="2018-03-09T18:51:07Z" batter="592444" stand="R" b_height="6-2" pitcher="571927" p_throws="L" des="JaCoby Jones flies out to left fielder Ty Kelly.  " des_es="JaCoby Jones batea elevado de out a jardinero izquierdo Ty Kelly.  " event_num="106" event="Flyout" event_es="Elevado de Out" home_team_runs="0" away_team_runs="1"><pitch des="In play, out(s)" des_es="En juego, out(s)" id="104" type="X" code="X" tfs="185058" tfs_zulu="2018-03-09T18:50:58Z" x="111.56065367693273" y="132.97635135135138" event_num="104" sz_top="3.467" sz_bot="1.589"  cc="" mt=""/></atbat><atbat num="21" b="4" s="0" o="2" start_tfs="185108" start_tfs_zulu="2018-03-09T18:51:08Z" end_tfs_zulu="2018-03-09T18:52:31Z" batter="553988" stand="R" b_height="6-1" pitcher="571927" p_throws="L" des="Dixon Machado walks.  " des_es="Dixon Machado recibe base por bolas.  " event_num="113" event="Walk" event_es="Base por Bolas" home_team_runs="0" away_team_runs="1"><pitch des="Ball" des_es="Bola mala" id="108" type="B" code="B" tfs="185219" tfs_zulu="2018-03-09T18:52:19Z" x="144.54109050911376" y="169.6528716216217" event_num="108" sz_top="3.411" sz_bot="1.565"  cc="" mt=""/><pitch des="Ball" des_es="Bola mala" id="109" type="B" code="B" tfs="185222" tfs_zulu="2018-03-09T18:52:22Z" x="133.16852608422374" y="90.18707770270275" event_num="109" sz_top="3.411" sz_bot="1.565"  cc="" mt=""/><pitch des="Ball" des_es="Bola mala" id="110" type="B" code="B" tfs="185225" tfs_zulu="2018-03-09T18:52:25Z" x="62.65862664990575" y="108.52533783783788" event_num="110" sz_top="3.411" sz_bot="1.565"  cc="" mt=""/><pitch des="Ball" des_es="Bola mala" id="111" type="B" code="B" tfs="185228" tfs_zulu="2018-03-09T18:52:28Z" x="117.24693588937774" y="194.71516047297305" event_num="111" sz_top="3.411" sz_bot="1.565"  cc="" mt=""/><runner id="553988" start="" end="1B" event="Walk" event_num="113"/></atbat><atbat num="22" b="0" s="0" o="3" start_tfs="185248" start_tfs_zulu="2018-03-09T18:52:48Z" end_tfs_zulu="2018-03-09T18:53:03Z" batter="547982" stand="L" b_height="6-2" pitcher="571927" p_throws="L" des="Leonys Martin grounds out softly, third baseman Todd Frazier to first baseman Wilmer Flores.  " des_es="Leonys Martin batea rodado de out suavemente, tercera base Todd Frazier a primera base Wilmer Flores.  " event_num="117" event="Groundout" event_es="Roletazo de Out" home_team_runs="0" away_team_runs="1"><pitch des="In play, out(s)" des_es="En juego, out(s)" id="115" type="X" code="X" tfs="185253" tfs_zulu="2018-03-09T18:52:53Z" x="110.42339723444375" y="170.2641469594595" event_num="115" on_1b="553988" sz_top="3.467" sz_bot="1.589"  cc="" mt=""/><runner id="553988" start="1B" end="" event="Groundout" event_num="117"/></atbat></bottom></inning><inning num="4" away_team="nyn" home_team="det" next="Y"><top><action b="0" s="0" o="0" des="Pitching Change: Alex Wilson replaces Michael Fulmer.  " des_es="Cambio de Lanzador: Alex Wilson reemplaza a Michael Fulmer.  " event="Pitching Substitution" event_es="Cambio de Lanzador" tfs="185409" tfs_zulu="2018-03-09T18:54:09Z" player="543935" pitch="1" event_num="121" home_team_runs="0" away_team_runs="1"/><atbat num="23" b="0" s="0" o="1" start_tfs="185541" start_tfs_zulu="2018-03-09T18:55:41Z" end_tfs_zulu="2018-03-09T18:56:10Z" batter="527038" stand="R" b_height="6-3" pitcher="543935" p_throws="R" des="Wilmer Flores grounds out, shortstop Jose Iglesias to first baseman Miguel Cabrera.  " des_es="Wilmer Flores batea rodado de out, campo corto Jose Iglesias a primera base Miguel Cabrera.  " event_num="125" event="Groundout" event_es="Roletazo de Out" home_team_runs="0" away_team_runs="1"><pitch des="In play, out(s)" des_es="En juego, out(s)" id="123" type="X" code="X" tfs="185555" tfs_zulu="2018-03-09T18:55:55Z" x="108.14888434946575" y="149.48078547297303" event_num="123" sz_top="3.49" sz_bot="1.601"  cc="" mt=""/></atbat><atbat num="24" b="0" s="0" o="2" start_tfs="185617" start_tfs_zulu="2018-03-09T18:56:17Z" end_tfs_zulu="2018-03-09T18:56:53Z" batter="608700" stand="R" b_height="6-2" pitcher="543935" p_throws="R" des="Kevin Plawecki lines out sharply to shortstop Jose Iglesias.  " des_es="Kevin Plawecki batea l&#237;nea de out fuertemente a campo corto Jose Iglesias.  " event_num="129" event="Lineout" event_es="Línea de Out" home_team_runs="0" away_team_runs="1"><pitch des="In play, out(s)" des_es="En juego, out(s)" id="127" type="X" code="X" tfs="185645" tfs_zulu="2018-03-09T18:56:45Z" x="112.69791011942173" y="138.47782939189193" event_num="127" sz_top="3.467" sz_bot="1.589"  cc="" mt=""/></atbat><atbat num="25" b="0" s="3" o="3" start_tfs="185654" start_tfs_zulu="2018-03-09T18:56:54Z" end_tfs_zulu="2018-03-09T18:59:17Z" batter="446653" stand="L" b_height="6-1" pitcher="543935" p_throws="R" des="Jose Lobaton strikes out swinging.  " des_es="Jose Lobaton se poncha tir&#225;ndole.  " event_num="135" event="Strikeout" event_es="Ponche" home_team_runs="0" away_team_runs="1"><pitch des="Called Strike" des_es="Strike cantado" id="131" type="S" code="C" tfs="185908" tfs_zulu="2018-03-09T18:59:08Z" x="119.52144877435576" y="147.03568412162164" event_num="131" sz_top="3.411" sz_bot="1.565"  cc="" mt=""/><pitch des="Foul" des_es="Foul" id="132" type="S" code="F" tfs="185911" tfs_zulu="2018-03-09T18:59:11Z" x="113.83516656191074" y="116.47191722972978" event_num="132" sz_top="3.411" sz_bot="1.565"  cc="" mt=""/><pitch des="Swinging Strike" des_es="Strike tir&#225;ndole" id="133" type="S" code="S" tfs="185915" tfs_zulu="2018-03-09T18:59:15Z" x="120.65870521684475" y="181.2671030405406" event_num="133" sz_top="3.411" sz_bot="1.565"  cc="" mt=""/></atbat></top><bottom><atbat num="26" b="0" s="0" o="0" start_tfs="190056" start_tfs_zulu="2018-03-09T19:00:56Z" end_tfs_zulu="2018-03-09T19:02:50Z" batter="578428" stand="R" b_height="5-11" pitcher="571927" p_throws="L" des="Jose Iglesias singles on a line drive to right fielder Matthew den Dekker.  " des_es="Jose Iglesias pega sencillo con l&#237;nea a jardinero derecho Matthew den Dekker.  " event_num="140" event="Single" event_es="Sencillo" home_team_runs="0" away_team_runs="1"><pitch des="In play, no out" des_es="En juego, no out" id="138" type="X" code="D" tfs="190240" tfs_zulu="2018-03-09T19:02:40Z" x="104.16848680075424" y="132.36507601351354" event_num="138" sz_top="3.319" sz_bot="1.513"  cc="" mt=""/><runner id="578428" start="" end="1B" event="Single" event_num="140"/></atbat><atbat num="27" b="0" s="0" o="1" start_tfs="190309" start_tfs_zulu="2018-03-09T19:03:09Z" end_tfs_zulu="2018-03-09T19:04:38Z" batter="408234" stand="R" b_height="6-4" pitcher="571927" p_throws="L" des="Miguel Cabrera flies out to center fielder Juan Lagares.  " des_es="Miguel Cabrera batea elevado de out a jardinero central Juan Lagares.  " event_num="144" event="Flyout" event_es="Elevado de Out" home_team_runs="0" away_team_runs="1"><pitch des="In play, out(s)" des_es="En juego, out(s)" id="142" type="X" code="X" tfs="190428" tfs_zulu="2018-03-09T19:04:28Z" x="99.61946103079823" y="123.195945945946" event_num="142" on_1b="578428" sz_top="3.549" sz_bot="1.627"  cc="" mt=""/></atbat><atbat num="28" b="0" s="0" o="2" start_tfs="190440" start_tfs_zulu="2018-03-09T19:04:40Z" end_tfs_zulu="2018-03-09T19:07:04Z" batter="592206" stand="R" b_height="6-4" pitcher="571927" p_throws="L" des="Nicholas Castellanos flies out to right fielder Matthew den Dekker.  " des_es="Nicholas Castellanos batea elevado de out a jardinero derecho Matthew den Dekker.  " event_num="148" event="Flyout" event_es="Elevado de Out" home_team_runs="0" away_team_runs="1"><pitch des="In play, out(s)" des_es="En juego, out(s)" id="146" type="X" code="X" tfs="190653" tfs_zulu="2018-03-09T19:06:53Z" x="100.18808925204273" y="122.58467060810815" event_num="146" on_1b="578428" sz_top="3.549" sz_bot="1.627"  cc="" mt=""/></atbat><atbat num="29" b="0" s="3" o="3" start_tfs="190706" start_tfs_zulu="2018-03-09T19:07:06Z" end_tfs_zulu="2018-03-09T19:09:09Z" batter="400121" stand="R" b_height="6-2" pitcher="571927" p_throws="L" des="Victor Martinez strikes out swinging.  " des_es="Victor Martinez se poncha tir&#225;ndole.  " event_num="154" event="Strikeout" event_es="Ponche" home_team_runs="0" away_team_runs="1"><pitch des="Foul" des_es="Foul" id="150" type="S" code="F" tfs="190902" tfs_zulu="2018-03-09T19:09:02Z" x="95.07043526084225" y="126.86359797297303" event_num="150" on_1b="578428" sz_top="3.467" sz_bot="1.589"  cc="" mt=""/><pitch des="Called Strike" des_es="Strike cantado" id="151" type="S" code="C" tfs="190905" tfs_zulu="2018-03-09T19:09:05Z" x="109.85476901319925" y="159.26119087837847" event_num="151" on_1b="578428" sz_top="3.467" sz_bot="1.589"  cc="" mt=""/><pitch des="Swinging Strike" des_es="Strike tir&#225;ndole" id="152" type="S" code="S" tfs="190908" tfs_zulu="2018-03-09T19:09:08Z" x="94.50180703959774" y="96.29983108108114" event_num="152" on_1b="578428" sz_top="3.467" sz_bot="1.589"  cc="" mt=""/><runner id="578428" start="1B" end="" event="Strikeout" event_num="154"/></atbat></bottom></inning><inning num="5" away_team="nyn" home_team="det" next="Y"><top><atbat num="30" b="0" s="0" o="1" start_tfs="191056" start_tfs_zulu="2018-03-09T19:10:56Z" end_tfs_zulu="2018-03-09T19:12:37Z" batter="608325" stand="R" b_height="6-2" pitcher="543935" p_throws="R" des="Gavin Cecchini flies out softly to left fielder JaCoby Jones.  " des_es="Gavin Cecchini batea elevado de out suavemente a jardinero izquierdo JaCoby Jones.  " event_num="160" event="Flyout" event_es="Elevado de Out" home_team_runs="0" away_team_runs="1"><pitch des="In play, out(s)" des_es="En juego, out(s)" id="158" type="X" code="X" tfs="191223" tfs_zulu="2018-03-09T19:12:23Z" x="111.56065367693273" y="128.69742398648654" event_num="158" sz_top="3.467" sz_bot="1.589"  cc="" mt=""/></atbat><atbat num="31" b="0" s="0" o="2" start_tfs="191239" start_tfs_zulu="2018-03-09T19:12:39Z" end_tfs_zulu="2018-03-09T19:13:04Z" batter="544925" stand="L" b_height="6-2" pitcher="543935" p_throws="R" des="Matthew den Dekker grounds out, second baseman Dixon Machado to first baseman Miguel Cabrera.  " des_es="Matthew den Dekker batea rodado de out, segunda base Dixon Machado a primera base Miguel Cabrera.  " event_num="164" event="Groundout" event_es="Roletazo de Out" home_team_runs="0" away_team_runs="1"><pitch des="In play, out(s)" des_es="En juego, out(s)" id="162" type="X" code="X" tfs="191253" tfs_zulu="2018-03-09T19:12:53Z" x="100.18808925204273" y="154.98226351351357" event_num="162" sz_top="3.467" sz_bot="1.589"  cc="" mt=""/></atbat><atbat num="32" b="0" s="0" o="3" start_tfs="191305" start_tfs_zulu="2018-03-09T19:13:05Z" end_tfs_zulu="2018-03-09T19:14:34Z" batter="571841" stand="L" b_height="6-0" pitcher="543935" p_throws="R" des="Ty Kelly flies out to right fielder Nicholas Castellanos.  " des_es="Ty Kelly batea elevado de out a jardinero derecho Nicholas Castellanos.  " event_num="168" event="Flyout" event_es="Elevado de Out" home_team_runs="0" away_team_runs="1"><pitch des="In play, out(s)" des_es="En juego, out(s)" id="166" type="X" code="X" tfs="191425" tfs_zulu="2018-03-09T19:14:25Z" x="107.58025612822125" y="131.1425253378379" event_num="166" sz_top="3.371" sz_bot="1.535"  cc="" mt=""/></atbat></top><bottom><action b="0" s="0" o="0" des="Pitching Change: Hansel Robles replaces Steven Matz.  " des_es="Cambio de Lanzador: Hansel Robles reemplaza a Steven Matz.  " event="Pitching Substitution" event_es="Cambio de Lanzador" tfs="191535" tfs_zulu="2018-03-09T19:15:35Z" player="570663" pitch="1" event_num="171" home_team_runs="0" away_team_runs="1"/><atbat num="33" b="0" s="0" o="0" start_tfs="191702" start_tfs_zulu="2018-03-09T19:17:02Z" end_tfs_zulu="2018-03-09T19:19:38Z" batter="543510" stand="R" b_height="6-3" pitcher="570663" p_throws="R" des="James McCann singles on a sharp ground ball to left fielder Ty Kelly.  " des_es="James McCann pega sencillo con rodado fuerte a jardinero izquierdo Ty Kelly.  " event_num="175" event="Single" event_es="Sencillo" home_team_runs="0" away_team_runs="1"><pitch des="In play, no out" des_es="En juego, no out" id="173" type="X" code="D" tfs="191923" tfs_zulu="2018-03-09T19:19:23Z" x="116.67830766813326" y="124.41849662162167" event_num="173" sz_top="3.49" sz_bot="1.601"  cc="" mt=""/><runner id="543510" start="" end="1B" event="Single" event_num="175"/></atbat><atbat num="34" b="0" s="0" o="0" start_tfs="191939" start_tfs_zulu="2018-03-09T19:19:39Z" end_tfs_zulu="2018-03-09T19:21:22Z" batter="600869" stand="L" b_height="6-1" pitcher="570663" p_throws="R" des="Jeimer Candelario doubles (4) on a line drive to right fielder Matthew den Dekker.   James McCann to 3rd.  " des_es="Jeimer Candelario pega doble (4) con l&#237;nea a jardinero derecho Matthew den Dekker.   James McCann a 3ra.  " event_num="180" event="Double" event_es="Doble" home_team_runs="0" away_team_runs="1"><pitch des="In play, no out" des_es="En juego, no out" id="177" type="X" code="D" tfs="192109" tfs_zulu="2018-03-09T19:21:09Z" x="100.18808925204273" y="119.52829391891898" event_num="177" on_1b="543510" sz_top="3.411" sz_bot="1.565"  cc="" mt=""/><runner id="543510" start="1B" end="3B" event="Double" event_num="180"/><runner id="600869" start="" end="2B" event="Double" event_num="180"/></atbat><atbat num="35" b="1" s="2" o="0" start_tfs="192124" start_tfs_zulu="2018-03-09T19:21:24Z" end_tfs_zulu="2018-03-09T19:23:36Z" batter="592444" stand="R" b_height="6-2" pitcher="570663" p_throws="R" des="JaCoby Jones homers (1) on a fly ball to left center field.   James McCann scores.    Jeimer Candelario scores.  " des_es="JaCoby Jones batea jonr&#243;n (1) con elevado entre los jardines izquierdo y central.   James McCann anota  Jeimer Candelario anota .  " event_num="192" event="Home Run" event_es="Jonr&#243;n" score="T" home_team_runs="3" away_team_runs="1"><pitch des="Foul" des_es="Foul" id="182" type="S" code="F" tfs="192317" tfs_zulu="2018-03-09T19:23:17Z" x="112.12928189817724" y="125.64104729729736" event_num="182" on_2b="600869" on_3b="543510" sz_top="3.467" sz_bot="1.589"  cc="" mt=""/><pitch des="Ball" des_es="Bola mala" id="183" type="B" code="B" tfs="192321" tfs_zulu="2018-03-09T19:23:21Z" x="117.24693588937774" y="190.43623310810818" event_num="183" on_2b="600869" on_3b="543510" sz_top="3.467" sz_bot="1.589"  cc="" mt=""/><pitch des="Called Strike" des_es="Strike cantado" id="184" type="S" code="C" tfs="192324" tfs_zulu="2018-03-09T19:23:24Z" x="102.46260213702072" y="142.7567567567568" event_num="184" on_2b="600869" on_3b="543510" sz_top="3.467" sz_bot="1.589"  cc="" mt=""/><pitch des="In play, run(s)" des_es="En juego, carrera(s)" id="185" type="X" code="E" tfs="192328" tfs_zulu="2018-03-09T19:23:28Z" x="114.97242300439974" y="116.47191722972978" event_num="185" on_2b="600869" on_3b="543510" sz_top="3.467" sz_bot="1.589"  cc="" mt=""/><runner id="600869" start="2B" end="" event="Home Run" event_num="192" score="T" rbi="T" earned="T"/><runner id="543510" start="3B" end="" event="Home Run" event_num="192" score="T" rbi="T" earned="T"/><runner id="592444" start="" end="" event="Home Run" event_num="192" score="T" rbi="T" earned="T"/></atbat><atbat num="36" b="3" s="1" o="0" start_tfs="192338" start_tfs_zulu="2018-03-09T19:23:38Z" end_tfs_zulu="2018-03-09T19:25:32Z" batter="553988" stand="R" b_height="6-1" pitcher="570663" p_throws="R" des="Dixon Machado homers (1) on a fly ball to left field.  " des_es="Dixon Machado batea jonr&#243;n (1) con elevado por el jard&#237;n izquierdo.  " event_num="201" event="Home Run" event_es="Jonr&#243;n" score="T" home_team_runs="4" away_team_runs="1"><pitch des="Ball" des_es="Bola mala" id="194" type="B" code="B" tfs="192513" tfs_zulu="2018-03-09T19:25:13Z" x="147.38423161533626" y="147.6469594594595" event_num="194" sz_top="3.411" sz_bot="1.565"  cc="" mt=""/><pitch des="Ball" des_es="Bola mala" id="195" type="B" code="B" tfs="192516" tfs_zulu="2018-03-09T19:25:16Z" x="77.44296040226276" y="97.5223817567568" event_num="195" sz_top="3.411" sz_bot="1.565"  cc="" mt=""/><pitch des="Ball" des_es="Bola mala" id="196" type="B" code="B" tfs="192518" tfs_zulu="2018-03-09T19:25:18Z" x="69.48216530483975" y="148.25823479729735" event_num="196" sz_top="3.411" sz_bot="1.565"  cc="" mt=""/><pitch des="Called Strike" des_es="Strike cantado" id="197" type="S" code="C" tfs="192522" tfs_zulu="2018-03-09T19:25:22Z" x="104.16848680075424" y="154.98226351351357" event_num="197" sz_top="3.411" sz_bot="1.565"  cc="" mt=""/><pitch des="In play, run(s)" des_es="En juego, carrera(s)" id="198" type="X" code="E" tfs="192525" tfs_zulu="2018-03-09T19:25:25Z" x="114.40379478315523" y="120.75084459459465" event_num="198" sz_top="3.411" sz_bot="1.565"  cc="" mt=""/><runner id="553988" start="" end="" event="Home Run" event_num="201" score="T" rbi="T" earned="T"/></atbat><action b="0" s="0" o="0" des="Coaching visit to mound.  " des_es="Visita del Instructor a la Lomita" event="Game Advisory" event_es="Aviso en el Juego" tfs="192626" tfs_zulu="2018-03-09T19:26:26Z" player="547982" pitch="0" event_num="203" home_team_runs="4" away_team_runs="1"/><atbat num="37" b="0" s="0" o="0" start_tfs="192535" start_tfs_zulu="2018-03-09T19:25:35Z" end_tfs_zulu="2018-03-09T19:28:23Z" batter="547982" stand="L" b_height="6-2" pitcher="570663" p_throws="R" des="Leonys Martin singles on a sharp ground ball to right fielder Matthew den Dekker.  " des_es="Leonys Martin pega sencillo con rodado fuerte a jardinero derecho Matthew den Dekker.  " event_num="206" event="Single" event_es="Sencillo" home_team_runs="4" away_team_runs="1"><pitch des="In play, no out" des_es="En juego, no out" id="204" type="X" code="D" tfs="192811" tfs_zulu="2018-03-09T19:28:11Z" x="103.03123035826523" y="149.48078547297303" event_num="204" sz_top="3.467" sz_bot="1.589"  cc="" mt=""/><runner id="547982" start="" end="1B" event="Single" event_num="206"/></atbat><atbat num="38" b="0" s="0" o="2" start_tfs="192825" start_tfs_zulu="2018-03-09T19:28:25Z" end_tfs_zulu="2018-03-09T19:29:44Z" batter="578428" stand="R" b_height="5-11" pitcher="570663" p_throws="R" des="Jose Iglesias grounds into a double play, third baseman Todd Frazier to second baseman Gavin Cecchini to first baseman Wilmer Flores.   Leonys Martin out at 2nd.  " des_es="Jose Iglesias batea rodado batea para doble matanza, tercera base Todd Frazier a segunda base Gavin Cecchini a primera base Wilmer Flores.   Leonys Martin a cabo a 2da.  " event_num="211" event="Grounded Into DP" event_es="Roletazo de Doble Play" home_team_runs="4" away_team_runs="1"><pitch des="In play, out(s)" des_es="En juego, out(s)" id="208" type="X" code="X" tfs="192935" tfs_zulu="2018-03-09T19:29:35Z" x="112.12928189817724" y="162.92884290540547" event_num="208" on_1b="547982" sz_top="3.319" sz_bot="1.513"  cc="" mt=""/><runner id="547982" start="1B" end="" event="Grounded Into DP" event_num="211"/></atbat><atbat num="39" b="0" s="0" o="3" start_tfs="192945" start_tfs_zulu="2018-03-09T19:29:45Z" end_tfs_zulu="2018-03-09T19:31:51Z" batter="408234" stand="R" b_height="6-4" pitcher="570663" p_throws="R" des="Miguel Cabrera flies out to right fielder Matthew den Dekker.  " des_es="Miguel Cabrera batea elevado de out a jardinero derecho Matthew den Dekker.  " event_num="215" event="Flyout" event_es="Elevado de Out" home_team_runs="4" away_team_runs="1"><pitch des="In play, out(s)" des_es="En juego, out(s)" id="213" type="X" code="X" tfs="193144" tfs_zulu="2018-03-09T19:31:44Z" x="97.34494814582024" y="120.75084459459465" event_num="213" sz_top="3.549" sz_bot="1.627"  cc="" mt=""/></atbat></bottom></inning><inning num="6" away_team="nyn" home_team="det" next="Y"><top><action b="0" s="0" o="0" des="Defensive Substitution: Mike Gerber replaces center fielder Leonys Martin, batting 1st, playing center field.  " des_es="Sustituci&#243;n a la Defensiva: Mike Gerber reemplaza a jardinero central Leonys Martin, como primer bate y jugando en el jardinero central.  " event="Defensive Sub" event_es="Sustituci&#243;n Defensiva" tfs="193339" tfs_zulu="2018-03-09T19:33:39Z" player="595222" pitch="1" event_num="218" home_team_runs="4" away_team_runs="1"/><action b="0" s="0" o="0" des="Defensive Substitution: Sergio Alcantara replaces shortstop Jose Iglesias, batting 2nd, playing shortstop.  " des_es="Sustituci&#243;n a la Defensiva: Sergio Alcantara reemplaza a campo corto Jose Iglesias, como segundo bate y jugando en el  campo corto.  " event="Defensive Sub" event_es="Sustituci&#243;n Defensiva" tfs="193339" tfs_zulu="2018-03-09T19:33:39Z" player="642727" pitch="1" event_num="220" home_team_runs="4" away_team_runs="1"/><action b="0" s="0" o="0" des="Defensive Substitution: John Hicks replaces first baseman Miguel Cabrera, batting 3rd, playing first base.  " des_es="Sustituci&#243;n a la Defensiva: John Hicks reemplaza a primera base Miguel Cabrera, como tercer bate y jugando en el primera base.  " event="Defensive Sub" event_es="Sustituci&#243;n Defensiva" tfs="193339" tfs_zulu="2018-03-09T19:33:39Z" player="543308" pitch="1" event_num="222" home_team_runs="4" away_team_runs="1"/><atbat num="40" b="0" s="0" o="1" start_tfs="193340" start_tfs_zulu="2018-03-09T19:33:40Z" end_tfs_zulu="2018-03-09T19:34:24Z" batter="501571" stand="R" b_height="6-1" pitcher="543935" p_throws="R" des="Juan Lagares flies out to right fielder Nicholas Castellanos.  " des_es="Juan Lagares batea elevado de out a jardinero derecho Nicholas Castellanos.  " event_num="226" event="Flyout" event_es="Elevado de Out" home_team_runs="4" away_team_runs="1"><pitch des="In play, out(s)" des_es="En juego, out(s)" id="224" type="X" code="X" tfs="193411" tfs_zulu="2018-03-09T19:34:11Z" x="100.75671747328724" y="132.97635135135138" event_num="224" sz_top="3.411" sz_bot="1.565"  cc="" mt=""/></atbat><atbat num="41" b="4" s="0" o="1" start_tfs="193425" start_tfs_zulu="2018-03-09T19:34:25Z" end_tfs_zulu="2018-03-09T19:36:47Z" batter="408314" stand="L" b_height="6-0" pitcher="543935" p_throws="R" des="Jose Reyes walks.  " des_es="Jose Reyes recibe base por bolas.  " event_num="233" event="Walk" event_es="Base por Bolas" home_team_runs="4" away_team_runs="1"><pitch des="Ball" des_es="Bola mala" id="228" type="B" code="B" tfs="193633" tfs_zulu="2018-03-09T19:36:33Z" x="113.26653834066624" y="85.29687500000004" event_num="228" sz_top="3.371" sz_bot="1.535"  cc="" mt=""/><pitch des="Ball" des_es="Bola mala" id="229" type="B" code="B" tfs="193636" tfs_zulu="2018-03-09T19:36:36Z" x="95.07043526084225" y="92.02090371621625" event_num="229" sz_top="3.371" sz_bot="1.535"  cc="" mt=""/><pitch des="Ball" des_es="Bola mala" id="230" type="B" code="B" tfs="193638" tfs_zulu="2018-03-09T19:36:38Z" x="143.97246228786923" y="140.9229307432433" event_num="230" sz_top="3.371" sz_bot="1.535"  cc="" mt=""/><pitch des="Ball" des_es="Bola mala" id="231" type="B" code="B" tfs="193643" tfs_zulu="2018-03-09T19:36:43Z" x="149.65874450031427" y="194.1038851351352" event_num="231" sz_top="3.371" sz_bot="1.535"  cc="" mt=""/><runner id="408314" start="" end="1B" event="Walk" event_num="233"/></atbat><action b="0" s="0" o="1" des="Offensive Substitution: Pinch-runner Luis Guillorme replaces Jose Reyes.  " des_es="Sustituci&#243;n a la ofensiva: corredor emergente Luis Guillorme reemplaza a replaces Jose Reyes.  " event="Offensive Sub" event_es="Cambio Defensivo" tfs="193713" tfs_zulu="2018-03-09T19:37:13Z" player="641645" pitch="4" event_num="235" home_team_runs="4" away_team_runs="1"/><atbat num="42" b="0" s="3" o="2" start_tfs="193750" start_tfs_zulu="2018-03-09T19:37:50Z" end_tfs_zulu="2018-03-09T19:39:48Z" batter="453943" stand="R" b_height="6-3" pitcher="543935" p_throws="R" des="Todd Frazier called out on strikes.  " des_es="Todd Frazier se poncha sin tirarle.  " event_num="241" event="Strikeout" event_es="Ponche" home_team_runs="4" away_team_runs="1"><pitch des="Foul" des_es="Foul" id="237" type="S" code="F" tfs="193934" tfs_zulu="2018-03-09T19:39:34Z" x="105.87437146448774" y="143.36803209459464" event_num="237" on_1b="641645" sz_top="3.49" sz_bot="1.601"  cc="" mt=""/><pitch des="Called Strike" des_es="Strike cantado" id="238" type="S" code="C" tfs="193938" tfs_zulu="2018-03-09T19:39:38Z" x="116.67830766813326" y="172.7092483108109" event_num="238" on_1b="641645" sz_top="3.49" sz_bot="1.601"  cc="" mt=""/><pitch des="Called Strike" des_es="Strike cantado" id="239" type="S" code="C" tfs="193944" tfs_zulu="2018-03-09T19:39:44Z" x="113.83516656191074" y="146.42440878378386" event_num="239" on_1b="641645" sz_top="3.49" sz_bot="1.601"  cc="" mt=""/></atbat><action b="0" s="0" o="2" des="With Wilmer Flores batting, Luis Guillorme advances to 2nd on a balk.  " des_es="Con Wilmer Flores bateando, Luis Guillorme avanza a la 2da por balk.  " event="Balk" event_es="Balk" tfs="194050" tfs_zulu="2018-03-09T19:40:50Z" player="641645" pitch="0" event_num="245" home_team_runs="4" away_team_runs="1"/><atbat num="43" b="1" s="2" o="2" start_tfs="193949" start_tfs_zulu="2018-03-09T19:39:49Z" end_tfs_zulu="2018-03-09T19:43:12Z" batter="527038" stand="R" b_height="6-3" pitcher="543935" p_throws="R" des="Wilmer Flores homers (1) on a fly ball to left center field.   Luis Guillorme scores.  " des_es="Wilmer Flores batea jonr&#243;n (1) con elevado entre los jardines izquierdo y central.   Luis Guillorme anota .  " event_num="254" event="Home Run" event_es="Jonr&#243;n" score="T" home_team_runs="4" away_team_runs="3"><runner id="641645" start="1B" end="2B" event="Balk" event_num="245"/><pitch des="Ball" des_es="Bola mala" id="246" type="B" code="B" tfs="194252" tfs_zulu="2018-03-09T19:42:52Z" x="106.44299968573225" y="94.46600506756761" event_num="246" on_2b="641645" sz_top="3.49" sz_bot="1.601"  cc="" mt=""/><pitch des="Called Strike" des_es="Strike cantado" id="247" type="S" code="C" tfs="194255" tfs_zulu="2018-03-09T19:42:55Z" x="113.26653834066624" y="140.31165540540547" event_num="247" on_2b="641645" sz_top="3.49" sz_bot="1.601"  cc="" mt=""/><pitch des="Foul" des_es="Foul" id="248" type="S" code="F" tfs="194258" tfs_zulu="2018-03-09T19:42:58Z" x="88.24689660590828" y="134.1989020270271" event_num="248" on_2b="641645" sz_top="3.49" sz_bot="1.601"  cc="" mt=""/><pitch des="In play, run(s)" des_es="En juego, carrera(s)" id="249" type="X" code="E" tfs="194304" tfs_zulu="2018-03-09T19:43:04Z" x="110.42339723444375" y="121.97339527027033" event_num="249" on_2b="641645" sz_top="3.49" sz_bot="1.601"  cc="" mt=""/><runner id="641645" start="2B" end="" event="Home Run" event_num="254" score="T" rbi="T" earned="T"/><runner id="527038" start="" end="" event="Home Run" event_num="254" score="T" rbi="T" earned="T"/></atbat><atbat num="44" b="0" s="0" o="3" start_tfs="194314" start_tfs_zulu="2018-03-09T19:43:14Z" end_tfs_zulu="2018-03-09T19:44:18Z" batter="608700" stand="R" b_height="6-2" pitcher="543935" p_throws="R" des="Kevin Plawecki lines out to center fielder Mike Gerber.  " des_es="Kevin Plawecki batea l&#237;nea de out a jardinero central Mike Gerber.  " event_num="258" event="Lineout" event_es="Línea de Out" home_team_runs="4" away_team_runs="3"><pitch des="In play, out(s)" des_es="En juego, out(s)" id="256" type="X" code="X" tfs="194412" tfs_zulu="2018-03-09T19:44:12Z" x="110.99202545568822" y="124.41849662162167" event_num="256" sz_top="3.467" sz_bot="1.589"  cc="" mt=""/></atbat></top><bottom><action b="0" s="0" o="0" des="Luis Guillorme remains in the game as the shortstop.  " des_es="Luis Guillorme permanece en el juego como el campo corto.  " event="Defensive Switch" event_es="Cambio Defensivo" tfs="194556" tfs_zulu="2018-03-09T19:45:56Z" player="641645" pitch="1" event_num="261" home_team_runs="4" away_team_runs="3"/><action b="0" s="0" o="0" des="Pitching Change: Paul Sewald replaces Hansel Robles.  " des_es="Cambio de Lanzador: Paul Sewald reemplaza a Hansel Robles.  " event="Pitching Substitution" event_es="Cambio de Lanzador" tfs="194556" tfs_zulu="2018-03-09T19:45:56Z" player="623149" pitch="1" event_num="263" home_team_runs="4" away_team_runs="3"/><atbat num="45" b="0" s="0" o="1" start_tfs="194646" start_tfs_zulu="2018-03-09T19:46:46Z" end_tfs_zulu="2018-03-09T19:47:57Z" batter="592206" stand="R" b_height="6-4" pitcher="623149" p_throws="R" des="Nicholas Castellanos flies out to center fielder Juan Lagares.  " des_es="Nicholas Castellanos batea elevado de out a jardinero central Juan Lagares.  " event_num="267" event="Flyout" event_es="Elevado de Out" home_team_runs="4" away_team_runs="3"><pitch des="In play, out(s)" des_es="En juego, out(s)" id="265" type="X" code="X" tfs="194750" tfs_zulu="2018-03-09T19:47:50Z" x="108.14888434946575" y="111.58171452702707" event_num="265" sz_top="3.549" sz_bot="1.627"  cc="" mt=""/></atbat><atbat num="46" b="0" s="0" o="1" start_tfs="194758" start_tfs_zulu="2018-03-09T19:47:58Z" end_tfs_zulu="2018-03-09T19:49:06Z" batter="400121" stand="L" b_height="6-2" pitcher="623149" p_throws="R" des="Victor Martinez hit by pitch.  " des_es="Victor Martinez golpeado por lanzamiento.  " event_num="270" event="Hit By Pitch" event_es="Pelotazo" home_team_runs="4" away_team_runs="3"><pitch des="Hit By Pitch" des_es="Pelotazo" id="269" type="B" code="" tfs="194906" tfs_zulu="2018-03-09T19:49:06Z" x="18.305625392834724" y="96.91110641891896" event_num="269" sz_top="3.467" sz_bot="1.589"  cc="" mt=""/><runner id="400121" start="" end="1B" event="Hit By Pitch" event_num="270"/></atbat><action b="0" s="0" o="1" des="Offensive Substitution: Pinch-runner Jim Adduci replaces Victor Martinez.  " des_es="Sustituci&#243;n a la ofensiva: corredor emergente Jim Adduci reemplaza a replaces Victor Martinez.  " event="Offensive Sub" event_es="Cambio Defensivo" tfs="194933" tfs_zulu="2018-03-09T19:49:33Z" player="451192" pitch="0" event_num="273" home_team_runs="4" away_team_runs="3"/><atbat num="47" b="0" s="3" o="2" start_tfs="194915" start_tfs_zulu="2018-03-09T19:49:15Z" end_tfs_zulu="2018-03-09T19:51:46Z" batter="543510" stand="R" b_height="6-3" pitcher="623149" p_throws="R" des="James McCann strikes out swinging.  " des_es="James McCann se poncha tir&#225;ndole.  " event_num="278" event="Strikeout" event_es="Ponche" home_team_runs="4" away_team_runs="3"><runner id="400121" start="1B" end="" event="Strikeout" event_num="278"/><runner id="451192" start="" end="1B" event="Strikeout" event_num="278"/><pitch des="Foul Tip" des_es="Foul atr&#225;s" id="274" type="S" code="T" tfs="195135" tfs_zulu="2018-03-09T19:51:35Z" x="121.79596165933374" y="142.14548141891896" event_num="274" on_1b="451192" sz_top="3.49" sz_bot="1.601"  cc="" mt=""/><pitch des="Swinging Strike" des_es="Strike tir&#225;ndole" id="275" type="S" code="S" tfs="195138" tfs_zulu="2018-03-09T19:51:38Z" x="92.79592237586422" y="168.430320945946" event_num="275" on_1b="451192" sz_top="3.49" sz_bot="1.601"  cc="" mt=""/><pitch des="Swinging Strike" des_es="Strike tir&#225;ndole" id="276" type="S" code="S" tfs="195141" tfs_zulu="2018-03-09T19:51:41Z" x="112.69791011942173" y="144.59058277027032" event_num="276" on_1b="451192" sz_top="3.49" sz_bot="1.601"  cc="" mt=""/></atbat><atbat num="48" b="0" s="0" o="3" start_tfs="195214" start_tfs_zulu="2018-03-09T19:52:14Z" end_tfs_zulu="2018-03-09T19:52:30Z" batter="600869" stand="L" b_height="6-1" pitcher="623149" p_throws="R" des="Jeimer Candelario grounds out softly, catcher Kevin Plawecki to first baseman Wilmer Flores.  " des_es="Jeimer Candelario batea rodado de out suavemente, receptor Kevin Plawecki a primera base Wilmer Flores.  " event_num="282" event="Groundout" event_es="Roletazo de Out" home_team_runs="4" away_team_runs="3"><pitch des="In play, out(s)" des_es="En juego, out(s)" id="280" type="X" code="X" tfs="195220" tfs_zulu="2018-03-09T19:52:20Z" x="109.85476901319925" y="158.64991554054063" event_num="280" on_1b="451192" sz_top="3.411" sz_bot="1.565"  cc="" mt=""/><runner id="451192" start="1B" end="" event="Groundout" event_num="282"/></atbat></bottom></inning><inning num="7" away_team="nyn" home_team="det" next="Y"><top><action b="0" s="0" o="0" des="Defensive Substitution: Harold Castro replaces right fielder Nicholas Castellanos, batting 4th, playing right field.  " des_es="Sustituci&#243;n a la Defensiva: Harold Castro reemplaza a jardinero derecho Nicholas Castellanos, como cuarto bate y jugando en el jardinero derecho.  " event="Defensive Sub" event_es="Sustituci&#243;n Defensiva" tfs="195431" tfs_zulu="2018-03-09T19:54:31Z" player="605612" pitch="1" event_num="286" home_team_runs="4" away_team_runs="3"/><action b="0" s="0" o="0" des="Jim Adduci remains in the game as the designated hitter.  " des_es="Jim Adduci permanece en el juego como el bateador designado.  " event="Defensive Switch" event_es="Cambio Defensivo" tfs="195431" tfs_zulu="2018-03-09T19:54:31Z" player="451192" pitch="1" event_num="288" home_team_runs="4" away_team_runs="3"/><action b="0" s="0" o="0" des="Defensive Substitution: Brayan Pena replaces catcher James McCann, batting 6th, playing catcher.  " des_es="Sustituci&#243;n a la Defensiva: Brayan Pena reemplaza a receptor James McCann, como sexto bate y jugando en el receptor.  " event="Defensive Sub" event_es="Sustituci&#243;n Defensiva" tfs="195431" tfs_zulu="2018-03-09T19:54:31Z" player="430910" pitch="1" event_num="290" home_team_runs="4" away_team_runs="3"/><action b="0" s="0" o="0" des="Defensive Substitution: Kody Eaves replaces third baseman Jeimer Candelario, batting 7th, playing third base.  " des_es="Sustituci&#243;n a la Defensiva: Kody Eaves reemplaza a tercera base Jeimer Candelario, como s&#233;ptimo bate y jugando en el tercera base.  " event="Defensive Sub" event_es="Sustituci&#243;n Defensiva" tfs="195431" tfs_zulu="2018-03-09T19:54:31Z" player="623238" pitch="1" event_num="292" home_team_runs="4" away_team_runs="3"/><action b="0" s="0" o="0" des="Defensive Substitution: Jason Krizan replaces left fielder JaCoby Jones, batting 8th, playing left field.  " des_es="Sustituci&#243;n a la Defensiva: Jason Krizan reemplaza a jardinero izquierdo JaCoby Jones, como octavo bate y jugando en el  jardinero izquierdo.  " event="Defensive Sub" event_es="Sustituci&#243;n Defensiva" tfs="195431" tfs_zulu="2018-03-09T19:54:31Z" player="607249" pitch="1" event_num="294" home_team_runs="4" away_team_runs="3"/><action b="0" s="0" o="0" des="Pitching Change: Enrique Burgos replaces Alex Wilson.  " des_es="Cambio de Lanzador: Enrique Burgos reemplaza a Alex Wilson.  " event="Pitching Substitution" event_es="Cambio de Lanzador" tfs="195431" tfs_zulu="2018-03-09T19:54:31Z" player="542609" pitch="1" event_num="296" home_team_runs="4" away_team_runs="3"/><action b="0" s="0" o="0" des="Offensive Substitution: Pinch-hitter Amed Rosario replaces Jose Lobaton.  " des_es="Sustituci&#243;n a la ofensiva: bateador emergente Amed Rosario reemplaza a Jose Lobaton.  " event="Offensive Sub" event_es="Cambio Defensivo" tfs="195445" tfs_zulu="2018-03-09T19:54:45Z" player="642708" pitch="1" event_num="298" home_team_runs="4" away_team_runs="3"/><atbat num="49" b="0" s="0" o="1" start_tfs="195528" start_tfs_zulu="2018-03-09T19:55:28Z" end_tfs_zulu="2018-03-09T19:56:04Z" batter="642708" stand="R" b_height="6-2" pitcher="542609" p_throws="R" des="Amed Rosario grounds out, third baseman Kody Eaves to first baseman John Hicks.  " des_es="Amed Rosario batea rodado de out, tercera base Kody Eaves a primera base John Hicks.  " event_num="302" event="Groundout" event_es="Roletazo de Out" home_team_runs="4" away_team_runs="3"><pitch des="In play, out(s)" des_es="En juego, out(s)" id="300" type="X" code="X" tfs="195557" tfs_zulu="2018-03-09T19:55:57Z" x="114.97242300439974" y="147.6469594594595" event_num="300" sz_top="3.467" sz_bot="1.589"  cc="" mt=""/></atbat><atbat num="50" b="0" s="0" o="1" start_tfs="195607" start_tfs_zulu="2018-03-09T19:56:07Z" end_tfs_zulu="2018-03-09T19:58:03Z" batter="608325" stand="R" b_height="6-2" pitcher="542609" p_throws="R" des="Gavin Cecchini triples (1) on a line drive to left fielder Jason Krizan.  " des_es="Gavin Cecchini pega triple (1) con l&#237;nea al jardinero izquierdo Jason Krizan.  " event_num="306" event="Triple" event_es="Triple" home_team_runs="4" away_team_runs="3"><pitch des="In play, no out" des_es="En juego, no out" id="304" type="X" code="D" tfs="195750" tfs_zulu="2018-03-09T19:57:50Z" x="114.40379478315523" y="130.53125000000006" event_num="304" sz_top="3.467" sz_bot="1.589"  cc="" mt=""/><runner id="608325" start="" end="3B" event="Triple" event_num="306"/></atbat><atbat num="51" b="0" s="3" o="2" start_tfs="195807" start_tfs_zulu="2018-03-09T19:58:07Z" end_tfs_zulu="2018-03-09T20:00:42Z" batter="544925" stand="L" b_height="6-2" pitcher="542609" p_throws="R" des="Matthew den Dekker called out on strikes.  " des_es="Matthew den Dekker se poncha sin tirarle.  " event_num="312" event="Strikeout" event_es="Ponche" home_team_runs="4" away_team_runs="3"><pitch des="Swinging Strike" des_es="Strike tir&#225;ndole" id="308" type="S" code="S" tfs="200015" tfs_zulu="2018-03-09T20:00:15Z" x="117.24693588937774" y="131.1425253378379" event_num="308" on_3b="608325" sz_top="3.467" sz_bot="1.589"  cc="" mt=""/><pitch des="Foul" des_es="Foul" id="309" type="S" code="F" tfs="200018" tfs_zulu="2018-03-09T20:00:18Z" x="96.77631992457573" y="142.7567567567568" event_num="309" on_3b="608325" sz_top="3.467" sz_bot="1.589"  cc="" mt=""/><pitch des="Called Strike" des_es="Strike cantado" id="310" type="S" code="C" tfs="200039" tfs_zulu="2018-03-09T20:00:39Z" x="110.99202545568822" y="147.6469594594595" event_num="310" on_3b="608325" sz_top="3.467" sz_bot="1.589"  cc="" mt=""/></atbat><atbat num="52" b="0" s="0" o="2" start_tfs="200107" start_tfs_zulu="2018-03-09T20:01:07Z" end_tfs_zulu="2018-03-09T20:01:20Z" batter="571841" stand="L" b_height="6-0" pitcher="542609" p_throws="R" des="Ty Kelly singles on a ground ball to right fielder Harold Castro.   Gavin Cecchini scores.  " des_es="Ty Kelly pega sencillo con rodado a jardinero derecho Harold Castro.   Gavin Cecchini anota.  " event_num="318" event="Single" event_es="Sencillo" score="T" home_team_runs="4" away_team_runs="4"><pitch des="In play, run(s)" des_es="En juego, carrera(s)" id="314" type="X" code="E" tfs="200111" tfs_zulu="2018-03-09T20:01:11Z" x="104.73711502199875" y="143.36803209459464" event_num="314" on_3b="608325" sz_top="3.371" sz_bot="1.535"  cc="" mt=""/><runner id="608325" start="3B" end="" event="Single" event_num="318" score="T" rbi="T" earned="T"/><runner id="571841" start="" end="1B" event="Single" event_num="318"/></atbat><atbat num="53" b="4" s="0" o="2" start_tfs="200128" start_tfs_zulu="2018-03-09T20:01:28Z" end_tfs_zulu="2018-03-09T20:05:31Z" batter="501571" stand="R" b_height="6-1" pitcher="542609" p_throws="R" des="Juan Lagares walks.   Ty Kelly to 2nd.  " des_es="Juan Lagares recibe base por bolas.   Ty Kelly a 2da.  " event_num="326" event="Walk" event_es="Base por Bolas" home_team_runs="4" away_team_runs="4"><pitch des="Ball" des_es="Bola mala" id="320" type="B" code="B" tfs="200515" tfs_zulu="2018-03-09T20:05:15Z" x="105.87437146448774" y="84.6855996621622" event_num="320" on_1b="571841" sz_top="3.411" sz_bot="1.565"  cc="" mt=""/><pitch des="Ball" des_es="Bola mala" id="321" type="B" code="B" tfs="200518" tfs_zulu="2018-03-09T20:05:18Z" x="65.50176775612825" y="105.46896114864869" event_num="321" on_1b="571841" sz_top="3.411" sz_bot="1.565"  cc="" mt=""/><pitch des="Ball" des_es="Bola mala" id="322" type="B" code="B" tfs="200522" tfs_zulu="2018-03-09T20:05:22Z" x="62.65862664990575" y="146.42440878378386" event_num="322" on_1b="571841" sz_top="3.411" sz_bot="1.565"  cc="" mt=""/><pitch des="Ball" des_es="Bola mala" id="323" type="B" code="B" tfs="200528" tfs_zulu="2018-03-09T20:05:28Z" x="144.54109050911376" y="151.92588682432435" event_num="323" on_1b="571841" sz_top="3.411" sz_bot="1.565"  cc="" mt=""/><runner id="571841" start="1B" end="2B" event="Walk" event_num="326"/><runner id="501571" start="" end="1B" event="Walk" event_num="326"/></atbat><atbat num="54" b="0" s="0" o="3" start_tfs="200610" start_tfs_zulu="2018-03-09T20:06:10Z" end_tfs_zulu="2018-03-09T20:06:48Z" batter="641645" stand="L" b_height="5-10" pitcher="542609" p_throws="R" des="Luis Guillorme grounds out softly, second baseman Dixon Machado to first baseman John Hicks.  " des_es="Luis Guillorme batea rodado de out suavemente, segunda base Dixon Machado a primera base John Hicks.  " event_num="330" event="Groundout" event_es="Roletazo de Out" home_team_runs="4" away_team_runs="4"><pitch des="In play, out(s)" des_es="En juego, out(s)" id="328" type="X" code="X" tfs="200639" tfs_zulu="2018-03-09T20:06:39Z" x="108.14888434946575" y="164.762668918919" event_num="328" on_1b="501571" on_2b="571841" sz_top="3.301" sz_bot="1.504"  cc="" mt=""/><runner id="501571" start="1B" end="" event="Groundout" event_num="330"/><runner id="571841" start="2B" end="" event="Groundout" event_num="330"/></atbat></top><bottom><action b="0" s="0" o="0" des="Defensive Substitution: Phillip Evans replaces center fielder Juan Lagares, batting 1st, playing right field.  " des_es="Sustituci&#243;n a la Defensiva: Phillip Evans reemplaza a jardinero central Juan Lagares, como primer bate y jugando en el jardinero derecho.  " event="Defensive Sub" event_es="Sustituci&#243;n Defensiva" tfs="200915" tfs_zulu="2018-03-09T20:09:15Z" player="595943" pitch="1" event_num="334" home_team_runs="4" away_team_runs="4"/><action b="0" s="0" o="0" des="Defensive Substitution: Tomas Nido replaces catcher Kevin Plawecki, batting 5th, playing catcher.  " des_es="Sustituci&#243;n a la Defensiva: Tomas Nido reemplaza a receptor Kevin Plawecki, como quinto bate y jugando en el receptor.  " event="Defensive Sub" event_es="Sustituci&#243;n Defensiva" tfs="200915" tfs_zulu="2018-03-09T20:09:15Z" player="621512" pitch="1" event_num="336" home_team_runs="4" away_team_runs="4"/><action b="0" s="0" o="0" des="Amed Rosario remains in the game as the designated hitter.  " des_es="Amed Rosario permanece en el juego como el bateador designado.  " event="Defensive Switch" event_es="Cambio Defensivo" tfs="200915" tfs_zulu="2018-03-09T20:09:15Z" player="642708" pitch="1" event_num="338" home_team_runs="4" away_team_runs="4"/><action b="0" s="0" o="0" des="Defensive switch from right field to center field for Matthew den Dekker.  " des_es="Sustituci&#243;n a la defensiva de jardinero derecho a jardinero central por Matthew den Dekker.  " event="Defensive Switch" event_es="Cambio Defensivo" tfs="200915" tfs_zulu="2018-03-09T20:09:15Z" player="544925" pitch="1" event_num="340" home_team_runs="4" away_team_runs="4"/><action b="0" s="0" o="0" des="Pitching Change: Tyler Bashlor replaces Paul Sewald.  " des_es="Cambio de Lanzador: Tyler Bashlor reemplaza a Paul Sewald.  " event="Pitching Substitution" event_es="Cambio de Lanzador" tfs="200915" tfs_zulu="2018-03-09T20:09:15Z" player="641341" pitch="1" event_num="342" home_team_runs="4" away_team_runs="4"/><atbat num="55" b="0" s="0" o="0" start_tfs="200917" start_tfs_zulu="2018-03-09T20:09:17Z" end_tfs_zulu="2018-03-09T20:10:08Z" batter="607249" stand="L" b_height="6-0" pitcher="641341" p_throws="R" des="Jason Krizan reaches on a fielding error by third baseman Todd Frazier.  " des_es="Jason Krizan se embasa por error en fildeo de tercera base Todd Frazier.  " event_num="347" event="Field Error" event_es="Error de Fildeo" home_team_runs="4" away_team_runs="4"><pitch des="In play, no out" des_es="En juego, no out" id="344" type="X" code="D" tfs="200955" tfs_zulu="2018-03-09T20:09:55Z" x="104.73711502199875" y="161.09501689189193" event_num="344" sz_top="3.371" sz_bot="1.535"  cc="" mt=""/><runner id="607249" start="" end="1B" event="Field Error" event_num="347"/></atbat><action b="0" s="0" o="0" des="Offensive Substitution: Pinch-hitter Alexi Amarista replaces Dixon Machado.  " des_es="Sustituci&#243;n a la ofensiva: bateador emergente Alexi Amarista reemplaza a Dixon Machado.  " event="Offensive Sub" event_es="Cambio Defensivo" tfs="201021" tfs_zulu="2018-03-09T20:10:21Z" player="506560" pitch="1" event_num="349" home_team_runs="4" away_team_runs="4"/><atbat num="56" b="4" s="0" o="0" start_tfs="201024" start_tfs_zulu="2018-03-09T20:10:24Z" end_tfs_zulu="2018-03-09T20:12:18Z" batter="506560" stand="L" b_height="5-6" pitcher="641341" p_throws="R" des="Alexi Amarista walks.   Jason Krizan to 2nd.  " des_es="Alexi Amarista recibe base por bolas.   Jason Krizan a 2da.  " event_num="357" event="Walk" event_es="Base por Bolas" home_team_runs="4" away_team_runs="4"><pitch des="Ball" des_es="Bola mala" id="351" type="B" code="B" tfs="201204" tfs_zulu="2018-03-09T20:12:04Z" x="113.83516656191074" y="103.02385979729735" event_num="351" on_1b="607249" sz_top="3.104" sz_bot="1.448"  cc="" mt=""/><pitch des="Ball" des_es="Bola mala" id="352" type="B" code="B" tfs="201207" tfs_zulu="2018-03-09T20:12:07Z" x="61.521370207416744" y="150.09206081081086" event_num="352" on_1b="607249" sz_top="3.104" sz_bot="1.448"  cc="" mt=""/><pitch des="Ball" des_es="Bola mala" id="353" type="B" code="B" tfs="201210" tfs_zulu="2018-03-09T20:12:10Z" x="132.03126964173475" y="196.54898648648657" event_num="353" on_1b="607249" sz_top="3.104" sz_bot="1.448"  cc="" mt=""/><pitch des="Ball" des_es="Bola mala" id="354" type="B" code="B" tfs="201215" tfs_zulu="2018-03-09T20:12:15Z" x="147.95285983658076" y="148.8695101351352" event_num="354" on_1b="607249" sz_top="3.104" sz_bot="1.448"  cc="" mt=""/><runner id="607249" start="1B" end="2B" event="Walk" event_num="357"/><runner id="506560" start="" end="1B" event="Walk" event_num="357"/></atbat><action b="0" s="1" o="1" des="With Mike Gerber batting, Tomas Nido picks off Jason Krizan at 2nd on throw to Luis Guillorme.  " des_es="Con Mike Gerber bateando, Tomas Nido sorprende a Jason Krizan en la 2da con disparo a Luis Guillorme.  " event="Pickoff 2B" event_es="Out en Viraje a 2B" tfs="201425" tfs_zulu="2018-03-09T20:14:25Z" player="607249" pitch="1" event_num="363" home_team_runs="4" away_team_runs="4"/><atbat num="57" b="0" s="1" o="1" start_tfs="201220" start_tfs_zulu="2018-03-09T20:12:20Z" end_tfs_zulu="2018-03-09T20:15:27Z" batter="595222" stand="L" b_height="6-0" pitcher="641341" p_throws="R" des="Mike Gerber singles on a line drive to right fielder Phillip Evans.   Alexi Amarista to 3rd.  " des_es="Mike Gerber pega sencillo con l&#237;nea a jardinero derecho Phillip Evans.   Alexi Amarista a 3ra.  " event_num="368" event="Single" event_es="Sencillo" home_team_runs="4" away_team_runs="4"><pitch des="Swinging Strike" des_es="Strike tir&#225;ndole" id="359" type="S" code="S" tfs="201405" tfs_zulu="2018-03-09T20:14:05Z" x="122.36458988057825" y="134.1989020270271" event_num="359" on_1b="506560" on_2b="607249" sz_top="3.371" sz_bot="1.535"  cc="" mt=""/><po des="Pickoff Attempt 2B"  des_es="Viraje a 2B" event_num="360" catcher="true" /><po des="Pickoff 2B"  des_es="Out en Viraje a 2B" event_num="361" /><runner id="607249" start="2B" end="" event="Pickoff 2B" event_num="363"/><pitch des="In play, no out" des_es="En juego, no out" id="364" type="X" code="D" tfs="201510" tfs_zulu="2018-03-09T20:15:10Z" x="109.85476901319925" y="151.92588682432435" event_num="364" on_1b="506560" sz_top="3.371" sz_bot="1.535"  cc="" mt=""/><runner id="506560" start="1B" end="3B" event="Single" event_num="368"/><runner id="595222" start="" end="1B" event="Single" event_num="368"/></atbat><atbat num="58" b="0" s="0" o="3" start_tfs="201529" start_tfs_zulu="2018-03-09T20:15:29Z" end_tfs_zulu="2018-03-09T20:17:15Z" batter="642727" stand="L" b_height="5-9" pitcher="641341" p_throws="R" des="Sergio Alcantara flies into a double play, right fielder Phillip Evans to catcher Tomas Nido.   Alexi Amarista out at home.  " des_es="Sergio Alcantara batea elevado para doble matanza, jardinero derecho Phillip Evans a receptor Tomas Nido.   Alexi Amarista a cabo a home.  " event_num="373" event="Double Play" event_es="Doble-Play" home_team_runs="4" away_team_runs="4"><pitch des="In play, out(s)" des_es="En juego, out(s)" id="370" type="X" code="X" tfs="201645" tfs_zulu="2018-03-09T20:16:45Z" x="105.87437146448774" y="129.91997466216222" event_num="370" on_1b="595222" on_3b="506560" sz_top="3.285" sz_bot="1.487"  cc="" mt=""/><runner id="595222" start="1B" end="" event="Double Play" event_num="373"/><runner id="506560" start="3B" end="" event="Double Play" event_num="373"/></atbat></bottom></inning><inning num="8" away_team="nyn" home_team="det" next="Y"><top><action b="0" s="0" o="0" des="Alexi Amarista remains in the game as the second baseman.  " des_es="Alexi Amarista permanece en el juego como el segunda base.  " event="Defensive Switch" event_es="Cambio Defensivo" tfs="201814" tfs_zulu="2018-03-09T20:18:14Z" player="506560" pitch="1" event_num="377" home_team_runs="4" away_team_runs="4"/><action b="0" s="0" o="0" des="Pitching Change: Mark Montgomery replaces Enrique Burgos.  " des_es="Cambio de Lanzador: Mark Montgomery reemplaza a Enrique Burgos.  " event="Pitching Substitution" event_es="Cambio de Lanzador" tfs="201814" tfs_zulu="2018-03-09T20:18:14Z" player="605384" pitch="1" event_num="379" home_team_runs="4" away_team_runs="4"/><atbat num="59" b="0" s="3" o="1" start_tfs="201937" start_tfs_zulu="2018-03-09T20:19:37Z" end_tfs_zulu="2018-03-09T20:22:49Z" batter="453943" stand="R" b_height="6-3" pitcher="605384" p_throws="R" des="Todd Frazier called out on strikes.  " des_es="Todd Frazier se poncha sin tirarle.  " event_num="385" event="Strikeout" event_es="Ponche" home_team_runs="4" away_team_runs="4"><pitch des="Swinging Strike" des_es="Strike tir&#225;ndole" id="381" type="S" code="S" tfs="202239" tfs_zulu="2018-03-09T20:22:39Z" x="113.83516656191074" y="159.26119087837847" event_num="381" sz_top="3.49" sz_bot="1.601"  cc="" mt=""/><pitch des="Foul" des_es="Foul" id="382" type="S" code="F" tfs="202244" tfs_zulu="2018-03-09T20:22:44Z" x="97.34494814582024" y="133.58762668918922" event_num="382" sz_top="3.49" sz_bot="1.601"  cc="" mt=""/><pitch des="Called Strike" des_es="Strike cantado" id="383" type="S" code="C" tfs="202248" tfs_zulu="2018-03-09T20:22:48Z" x="100.75671747328724" y="173.3205236486487" event_num="383" sz_top="3.49" sz_bot="1.601"  cc="" mt=""/></atbat><atbat num="60" b="0" s="0" o="1" start_tfs="202251" start_tfs_zulu="2018-03-09T20:22:51Z" end_tfs_zulu="2018-03-09T20:24:56Z" batter="527038" stand="R" b_height="6-3" pitcher="605384" p_throws="R" des="Wilmer Flores singles on a line drive to right fielder Harold Castro.  " des_es="Wilmer Flores pega sencillo con l&#237;nea a jardinero derecho Harold Castro.  " event_num="389" event="Single" event_es="Sencillo" home_team_runs="4" away_team_runs="4"><pitch des="In play, no out" des_es="En juego, no out" id="387" type="X" code="D" tfs="202442" tfs_zulu="2018-03-09T20:24:42Z" x="101.32534569453173" y="129.91997466216222" event_num="387" sz_top="3.49" sz_bot="1.601"  cc="" mt=""/><runner id="527038" start="" end="1B" event="Single" event_num="389"/></atbat><atbat num="61" b="0" s="0" o="2" start_tfs="202458" start_tfs_zulu="2018-03-09T20:24:58Z" end_tfs_zulu="2018-03-09T20:25:56Z" batter="621512" stand="R" b_height="6-0" pitcher="605384" p_throws="R" des="Tomas Nido flies out to right fielder Harold Castro.  " des_es="Tomas Nido batea elevado de out a jardinero derecho Harold Castro.  " event_num="393" event="Flyout" event_es="Elevado de Out" home_team_runs="4" away_team_runs="4"><pitch des="In play, out(s)" des_es="En juego, out(s)" id="391" type="X" code="X" tfs="202542" tfs_zulu="2018-03-09T20:25:42Z" x="101.89397391577623" y="129.91997466216222" event_num="391" on_1b="527038" sz_top="3.371" sz_bot="1.535"  cc="" mt=""/></atbat><atbat num="62" b="0" s="0" o="3" start_tfs="202559" start_tfs_zulu="2018-03-09T20:25:59Z" end_tfs_zulu="2018-03-09T20:28:38Z" batter="642708" stand="R" b_height="6-2" pitcher="605384" p_throws="R" des="Amed Rosario grounds out softly, third baseman Kody Eaves to first baseman John Hicks.  " des_es="Amed Rosario batea rodado de out suavemente, tercera base Kody Eaves a primera base John Hicks.  " event_num="397" event="Groundout" event_es="Roletazo de Out" home_team_runs="4" away_team_runs="4"><pitch des="In play, out(s)" des_es="En juego, out(s)" id="395" type="X" code="X" tfs="202827" tfs_zulu="2018-03-09T20:28:27Z" x="110.42339723444375" y="156.20481418918925" event_num="395" on_1b="527038" sz_top="3.467" sz_bot="1.589"  cc="" mt=""/><runner id="527038" start="1B" end="" event="Groundout" event_num="397"/></atbat></top><bottom><action b="0" s="0" o="0" des="Defensive Substitution: David Thompson replaces third baseman Todd Frazier, batting 3rd, playing third base.  " des_es="Sustituci&#243;n a la Defensiva: David Thompson reemplaza a tercera base Todd Frazier, como tercer bate y jugando en el tercera base.  " event="Defensive Sub" event_es="Sustituci&#243;n Defensiva" tfs="203050" tfs_zulu="2018-03-09T20:30:50Z" player="621420" pitch="1" event_num="401" home_team_runs="4" away_team_runs="4"/><action b="0" s="0" o="0" des="Defensive Substitution: Peter Alonso replaces first baseman Wilmer Flores, batting 4th, playing first base.  " des_es="Sustituci&#243;n a la Defensiva: Peter Alonso reemplaza a primera base Wilmer Flores, como cuarto bate y jugando en el primera base.  " event="Defensive Sub" event_es="Sustituci&#243;n Defensiva" tfs="203050" tfs_zulu="2018-03-09T20:30:50Z" player="624413" pitch="1" event_num="403" home_team_runs="4" away_team_runs="4"/><action b="0" s="0" o="0" des="Defensive Substitution: L.  J.   Mazzilli replaces left fielder Ty Kelly, batting 9th, playing left field.  " des_es="Sustituci&#243;n a la Defensiva: L.  J.   Mazzilli reemplaza a jardinero izquierdo Ty Kelly, como noveno bate y jugando en el jardinero izquierdo.  " event="Defensive Sub" event_es="Sustituci&#243;n Defensiva" tfs="203050" tfs_zulu="2018-03-09T20:30:50Z" player="608687" pitch="1" event_num="405" home_team_runs="4" away_team_runs="4"/><action b="0" s="0" o="0" des="Pitching Change: Corey Oswalt replaces Tyler Bashlor.  " des_es="Cambio de Lanzador: Corey Oswalt reemplaza a Tyler Bashlor.  " event="Pitching Substitution" event_es="Cambio de Lanzador" tfs="203050" tfs_zulu="2018-03-09T20:30:50Z" player="621261" pitch="1" event_num="407" home_team_runs="4" away_team_runs="4"/><atbat num="63" b="0" s="0" o="0" start_tfs="203053" start_tfs_zulu="2018-03-09T20:30:53Z" end_tfs_zulu="2018-03-09T20:32:08Z" batter="543308" stand="R" b_height="6-2" pitcher="621261" p_throws="R" des="John Hicks triples (1) on a fly ball to center fielder Matthew den Dekker.  " des_es="John Hicks pega triple (1) con elevado al jardinero central Matthew den Dekker.  " event_num="411" event="Triple" event_es="Triple" home_team_runs="4" away_team_runs="4"><pitch des="In play, no out" des_es="En juego, no out" id="409" type="X" code="D" tfs="203149" tfs_zulu="2018-03-09T20:31:49Z" x="100.18808925204273" y="117.69446790540545" event_num="409" sz_top="3.467" sz_bot="1.589"  cc="" mt=""/><runner id="543308" start="" end="3B" event="Triple" event_num="411"/></atbat><action b="0" s="0" o="0" des="Offensive Substitution: Pinch-runner Pete Kozma replaces John Hicks.  " des_es="Sustituci&#243;n a la ofensiva: corredor emergente Pete Kozma reemplaza a replaces John Hicks.  " event="Offensive Sub" event_es="Cambio Defensivo" tfs="203232" tfs_zulu="2018-03-09T20:32:32Z" player="518902" pitch="1" event_num="413" home_team_runs="4" away_team_runs="4"/><atbat num="64" b="0" s="0" o="1" start_tfs="203301" start_tfs_zulu="2018-03-09T20:33:01Z" end_tfs_zulu="2018-03-09T20:33:16Z" batter="605612" stand="L" b_height="6-0" pitcher="621261" p_throws="R" des="Harold Castro grounds out, second baseman Gavin Cecchini to first baseman Peter Alonso.  " des_es="Harold Castro batea rodado de out, segunda base Gavin Cecchini a primera base Peter Alonso.  " event_num="417" event="Groundout" event_es="Roletazo de Out" home_team_runs="4" away_team_runs="4"><pitch des="In play, out(s)" des_es="En juego, out(s)" id="415" type="X" code="X" tfs="203305" tfs_zulu="2018-03-09T20:33:05Z" x="105.87437146448774" y="163.5401182432433" event_num="415" on_3b="518902" sz_top="3.371" sz_bot="1.535"  cc="" mt=""/></atbat><atbat num="65" b="0" s="0" o="2" start_tfs="203319" start_tfs_zulu="2018-03-09T20:33:19Z" end_tfs_zulu="2018-03-09T20:33:53Z" batter="451192" stand="L" b_height="6-2" pitcher="621261" p_throws="R" des="Jim Adduci grounds out softly, shortstop Luis Guillorme to first baseman Peter Alonso.  " des_es="Jim Adduci batea rodado de out suavemente, campo corto Luis Guillorme a primera base Peter Alonso.  " event_num="421" event="Groundout" event_es="Roletazo de Out" home_team_runs="4" away_team_runs="4"><pitch des="In play, out(s)" des_es="En juego, out(s)" id="419" type="X" code="X" tfs="203339" tfs_zulu="2018-03-09T20:33:39Z" x="106.44299968573225" y="165.3739442567568" event_num="419" on_3b="518902" sz_top="3.467" sz_bot="1.589"  cc="" mt=""/></atbat><atbat num="66" b="0" s="0" o="3" start_tfs="203354" start_tfs_zulu="2018-03-09T20:33:54Z" end_tfs_zulu="2018-03-09T20:35:14Z" batter="430910" stand="L" b_height="5-9" pitcher="621261" p_throws="R" des="Brayan Pena grounds out, shortstop Luis Guillorme to first baseman Peter Alonso.  " des_es="Brayan Pena batea rodado de out, campo corto Luis Guillorme a primera base Peter Alonso.  " event_num="425" event="Groundout" event_es="Roletazo de Out" home_team_runs="4" away_team_runs="4"><pitch des="In play, out(s)" des_es="En juego, out(s)" id="423" type="X" code="X" tfs="203507" tfs_zulu="2018-03-09T20:35:07Z" x="101.32534569453173" y="156.20481418918925" event_num="423" on_3b="518902" sz_top="3.36" sz_bot="1.53"  cc="" mt=""/><runner id="518902" start="3B" end="" event="Groundout" event_num="425"/></atbat></bottom></inning><inning num="9" away_team="nyn" home_team="det" next="N"><top><action b="0" s="0" o="0" des="Defensive Substitution: Ronny Rodriguez replaces Pete Kozma, batting 3rd, playing first base.  " des_es="Sustituci&#243;n a la Defensiva: Ronny Rodriguez reemplaza a Pete Kozma, como tercer bate y jugando en el primera base.  " event="Defensive Sub" event_es="Sustituci&#243;n Defensiva" tfs="203631" tfs_zulu="2018-03-09T20:36:31Z" player="500135" pitch="1" event_num="429" home_team_runs="4" away_team_runs="4"/><action b="0" s="0" o="0" des="Pitching Change: Warwick Saupold replaces Mark Montgomery.  " des_es="Cambio de Lanzador: Warwick Saupold reemplaza a Mark Montgomery.  " event="Pitching Substitution" event_es="Cambio de Lanzador" tfs="203631" tfs_zulu="2018-03-09T20:36:31Z" player="599683" pitch="1" event_num="431" home_team_runs="4" away_team_runs="4"/><atbat num="67" b="0" s="0" o="1" start_tfs="203715" start_tfs_zulu="2018-03-09T20:37:15Z" end_tfs_zulu="2018-03-09T20:38:20Z" batter="608325" stand="R" b_height="6-2" pitcher="599683" p_throws="R" des="Gavin Cecchini pops out to third baseman Kody Eaves in foul territory.  " des_es="Gavin Cecchini batea elevadito de out a tercera base Kody Eaves en territorio de foul.  " event_num="435" event="Pop Out" event_es="Elevado de Out" home_team_runs="4" away_team_runs="4"><pitch des="In play, out(s)" des_es="En juego, out(s)" id="433" type="X" code="X" tfs="203808" tfs_zulu="2018-03-09T20:38:08Z" x="110.99202545568822" y="148.25823479729735" event_num="433" sz_top="3.467" sz_bot="1.589"  cc="" mt=""/></atbat><atbat num="68" b="0" s="3" o="2" start_tfs="203822" start_tfs_zulu="2018-03-09T20:38:22Z" end_tfs_zulu="2018-03-09T20:39:52Z" batter="544925" stand="L" b_height="6-2" pitcher="599683" p_throws="R" des="Matthew den Dekker strikes out swinging.  " des_es="Matthew den Dekker se poncha tir&#225;ndole.  " event_num="441" event="Strikeout" event_es="Ponche" home_team_runs="4" away_team_runs="4"><pitch des="Foul" des_es="Foul" id="437" type="S" code="F" tfs="203944" tfs_zulu="2018-03-09T20:39:44Z" x="110.99202545568822" y="125.64104729729736" event_num="437" sz_top="3.467" sz_bot="1.589"  cc="" mt=""/><pitch des="Called Strike" des_es="Strike cantado" id="438" type="S" code="C" tfs="203947" tfs_zulu="2018-03-09T20:39:47Z" x="100.75671747328724" y="164.762668918919" event_num="438" sz_top="3.467" sz_bot="1.589"  cc="" mt=""/><pitch des="Swinging Strike" des_es="Strike tir&#225;ndole" id="439" type="S" code="S" tfs="203951" tfs_zulu="2018-03-09T20:39:51Z" x="95.63906348208674" y="135.42145270270277" event_num="439" sz_top="3.467" sz_bot="1.589"  cc="" mt=""/></atbat><atbat num="69" b="0" s="0" o="3" start_tfs="203954" start_tfs_zulu="2018-03-09T20:39:54Z" end_tfs_zulu="2018-03-09T20:41:59Z" batter="608687" stand="R" b_height="6-1" pitcher="599683" p_throws="R" des="L.  J.   Mazzilli grounds out, second baseman Alexi Amarista to first baseman Ronny Rodriguez.  " des_es="L.  J.   Mazzilli batea rodado de out, segunda base Alexi Amarista a primera base Ronny Rodriguez.  " event_num="445" event="Groundout" event_es="Roletazo de Out" home_team_runs="4" away_team_runs="4"><pitch des="In play, out(s)" des_es="En juego, out(s)" id="443" type="X" code="X" tfs="204151" tfs_zulu="2018-03-09T20:41:51Z" x="105.87437146448774" y="145.20185810810815" event_num="443" sz_top="3.4" sz_bot="1.57"  cc="" mt=""/></atbat></top><bottom><atbat num="70" b="0" s="3" o="1" start_tfs="204341" start_tfs_zulu="2018-03-09T20:43:41Z" end_tfs_zulu="2018-03-09T20:45:03Z" batter="623238" stand="L" b_height="6-0" pitcher="621261" p_throws="R" des="Kody Eaves called out on strikes.  " des_es="Kody Eaves se poncha sin tirarle.  " event_num="452" event="Strikeout" event_es="Ponche" home_team_runs="4" away_team_runs="4"><pitch des="Foul" des_es="Foul" id="448" type="S" code="F" tfs="204455" tfs_zulu="2018-03-09T20:44:55Z" x="115.54105122564425" y="126.2523226351352" event_num="448" sz_top="3.371" sz_bot="1.535"  cc="" mt=""/><pitch des="Swinging Strike" des_es="Strike tir&#225;ndole" id="449" type="S" code="S" tfs="204458" tfs_zulu="2018-03-09T20:44:58Z" x="105.30574324324323" y="157.42736486486493" event_num="449" sz_top="3.371" sz_bot="1.535"  cc="" mt=""/><pitch des="Called Strike" des_es="Strike cantado" id="450" type="S" code="C" tfs="204501" tfs_zulu="2018-03-09T20:45:01Z" x="110.42339723444375" y="152.5371621621622" event_num="450" sz_top="3.371" sz_bot="1.535"  cc="" mt=""/></atbat><atbat num="71" b="0" s="0" o="2" start_tfs="204504" start_tfs_zulu="2018-03-09T20:45:04Z" end_tfs_zulu="2018-03-09T20:45:34Z" batter="607249" stand="L" b_height="6-0" pitcher="621261" p_throws="R" des="Jason Krizan flies out to left fielder L.   Mazzilli.  " des_es="Jason Krizan batea elevado de out a jardinero izquierdo L.   Mazzilli.  " event_num="456" event="Flyout" event_es="Elevado de Out" home_team_runs="4" away_team_runs="4"><pitch des="In play, out(s)" des_es="En juego, out(s)" id="454" type="X" code="X" tfs="204525" tfs_zulu="2018-03-09T20:45:25Z" x="111.56065367693273" y="129.91997466216222" event_num="454" sz_top="3.371" sz_bot="1.535"  cc="" mt=""/></atbat><atbat num="72" b="0" s="0" o="3" start_tfs="204535" start_tfs_zulu="2018-03-09T20:45:35Z" end_tfs_zulu="2018-03-09T20:46:53Z" batter="506560" stand="L" b_height="5-6" pitcher="621261" p_throws="R" des="Alexi Amarista lines out to second baseman Gavin Cecchini.  " des_es="Alexi Amarista batea l&#237;nea de out a segunda base Gavin Cecchini.  " event_num="460" event="Lineout" event_es="Línea de Out" home_team_runs="4" away_team_runs="4"><pitch des="In play, out(s)" des_es="En juego, out(s)" id="458" type="X" code="X" tfs="204645" tfs_zulu="2018-03-09T20:46:45Z" x="105.30574324324323" y="162.3175675675676" event_num="458" sz_top="3.104" sz_bot="1.448"  cc="" mt=""/></atbat></bottom></inning></game>