<!--Copyright 2018 MLB Advanced Media, L.P.  Use of any content on this page acknowledges agreement to the terms posted here http://gdx.mlb.com/components/copyright.txt--><game atBat="596068" deck="453203" hole="607256" ind="F"><inning num="1" away_team="mil" home_team="cle" next="Y"><top><atbat num="1" b="1" s="3" o="1" start_tfs="200537" start_tfs_zulu="2016-03-13T20:05:37Z" end_tfs_zulu="2016-03-13T20:09:05Z" batter="542979" stand="R" b_height="6-3" pitcher="458708" p_throws="R" des="Keon Broxton called out on strikes.  " des_es="Keon Broxton se poncha sin tirarle.  " event_num="8" event="Strikeout" event_es="Ponche" home_team_runs="0" away_team_runs="0"><pitch des="Ball" des_es="Bola mala" id="3" type="B" code="B" tfs="200539" tfs_zulu="2016-03-13T20:05:39Z" x="110.07985101744188" y="81.05615234374999" event_num="3" sz_top="3.61" sz_bot="1.62"  cc="" mt=""/><pitch des="Called Strike" des_es="Strike cantado" id="4" type="S" code="C" tfs="200903" tfs_zulu="2016-03-13T20:09:03Z" x="107.44994549418607" y="148.90771484375" event_num="4" sz_top="3.61" sz_bot="1.62"  cc="" mt=""/><pitch des="Called Strike" des_es="Strike cantado" id="5" type="S" code="C" tfs="200903" tfs_zulu="2016-03-13T20:09:03Z" x="107.44994549418607" y="148.90771484375" event_num="5" sz_top="3.61" sz_bot="1.62"  cc="" mt=""/><pitch des="Called Strike" des_es="Strike cantado" id="6" type="S" code="C" tfs="200905" tfs_zulu="2016-03-13T20:09:05Z" x="107.44994549418607" y="148.90771484375" event_num="6" sz_top="3.61" sz_bot="1.62"  cc="" mt=""/></atbat><atbat num="2" b="0" s="0" o="1" start_tfs="200907" start_tfs_zulu="2016-03-13T20:09:07Z" end_tfs_zulu="2016-03-13T20:09:22Z" batter="518960" stand="R" b_height="6-0" pitcher="458708" p_throws="R" des="Jonathan Lucroy singles on a line drive to shortstop Francisco Lindor, deflected by pitcher Josh Tomlin.  " des_es="Jonathan Lucroy pega sencillo con l&#237;nea a campo corto Francisco Lindor, desviada por lanzador Josh Tomlin.  " event_num="12" event="Single" event_es="Sencillo" home_team_runs="0" away_team_runs="0"><pitch des="In play, no out" des_es="En juego, no out" id="10" type="X" code="D" tfs="200915" tfs_zulu="2016-03-13T20:09:15Z" x="114.90134447674419" y="133.82958984374997" event_num="10" sz_top="3.51" sz_bot="1.51"  cc="" mt=""/><runner id="518960" start="" end="1B" event="Single" event_num="12"/></atbat><atbat num="3" b="0" s="0" o="2" start_tfs="200923" start_tfs_zulu="2016-03-13T20:09:23Z" end_tfs_zulu="2016-03-13T20:12:31Z" batter="431094" stand="R" b_height="5-11" pitcher="458708" p_throws="R" des="Aaron Hill pops out to catcher Yan Gomes in foul territory.  " des_es="Aaron Hill batea elevadito de out a receptor Yan Gomes en territorio de foul.  " event_num="16" event="Pop Out" event_es="Elevado de Out" home_team_runs="0" away_team_runs="0"><pitch des="In play, out(s)" des_es="En juego, out(s)" id="14" type="X" code="X" tfs="201226" tfs_zulu="2016-03-13T20:12:26Z" x="104.38172238372093" y="132.88720703125" event_num="14" on_1b="518960" sz_top="3.32" sz_bot="1.45"  cc="" mt=""/></atbat><atbat num="4" b="1" s="1" o="2" start_tfs="201436" start_tfs_zulu="2016-03-13T20:14:36Z" end_tfs_zulu="2016-03-13T20:14:49Z" batter="543590" stand="L" b_height="6-3" pitcher="458708" p_throws="R" des="Kirk Nieuwenhuis homers (1) on a fly ball to right center field.    Jonathan Lucroy scores.  " des_es="Kirk Nieuwenhuis batea jonr&#243;n (1) con elevado entre los jardines izquierdo y central.    Jonathan Lucroy anota.  " event_num="25" event="Home Run" event_es="Jonr&#243;n" score="T" home_team_runs="0" away_team_runs="2"><pitch des="Ball" des_es="Bola mala" id="18" type="B" code="B" tfs="201437" tfs_zulu="2016-03-13T20:14:37Z" x="126.29760174418605" y="66.44921874999999" event_num="18" on_1b="518960" sz_top="3.38" sz_bot="1.58"  cc="" mt=""/><pitch des="Swinging Strike" des_es="Strike tir&#225;ndole" id="19" type="S" code="S" tfs="201439" tfs_zulu="2016-03-13T20:14:39Z" x="128.05087209302326" y="123.46337890624999" event_num="19" on_1b="518960" sz_top="3.38" sz_bot="1.58"  cc="" mt=""/><pitch des="In play, run(s)" des_es="En juego, carrera(s)" id="20" type="X" code="E" tfs="201441" tfs_zulu="2016-03-13T20:14:41Z" x="128.05087209302326" y="123.46337890624999" event_num="20" on_1b="518960" sz_top="3.38" sz_bot="1.58"  cc="" mt=""/><runner id="518960" start="1B" end="" event="Home Run" event_num="25" score="T" rbi="T" earned="T"/><runner id="543590" start="" end="" event="Home Run" event_num="25" score="T" rbi="T" earned="T"/></atbat><atbat num="5" b="0" s="3" o="3" start_tfs="201451" start_tfs_zulu="2016-03-13T20:14:51Z" end_tfs_zulu="2016-03-13T20:15:44Z" batter="542642" stand="R" b_height="6-0" pitcher="458708" p_throws="R" des="Rymer Liriano strikes out swinging.  " des_es="Rymer Liriano se poncha tir&#225;ndole.  " event_num="31" event="Strikeout" event_es="Ponche" home_team_runs="0" away_team_runs="2"><pitch des="Swinging Strike" des_es="Strike tir&#225;ndole" id="27" type="S" code="S" tfs="201542" tfs_zulu="2016-03-13T20:15:42Z" x="116.65461482558142" y="147.49414062499997" event_num="27" sz_top="3.4" sz_bot="1.52"  cc="" mt=""/><pitch des="Swinging Strike" des_es="Strike tir&#225;ndole" id="28" type="S" code="S" tfs="201542" tfs_zulu="2016-03-13T20:15:42Z" x="116.65461482558142" y="147.49414062499997" event_num="28" sz_top="3.4" sz_bot="1.52"  cc="" mt=""/><pitch des="Swinging Strike" des_es="Strike tir&#225;ndole" id="29" type="S" code="S" tfs="201544" tfs_zulu="2016-03-13T20:15:44Z" x="116.65461482558142" y="147.49414062499997" event_num="29" sz_top="3.4" sz_bot="1.52"  cc="" mt=""/></atbat></top><bottom><atbat num="6" b="0" s="0" o="1" start_tfs="201549" start_tfs_zulu="2016-03-13T20:15:49Z" end_tfs_zulu="2016-03-13T20:19:26Z" batter="434658" stand="R" b_height="5-10" pitcher="502624" p_throws="R" des="Rajai Davis grounds out, shortstop Jonathan Villar to first baseman Andy Wilkins.  " des_es="Rajai Davis batea rodado de out, campo corto Jonathan Villar a primera base Andy Wilkins.  " event_num="36" event="Groundout" event_es="Roletazo de Out" home_team_runs="0" away_team_runs="2"><pitch des="In play, out(s)" des_es="En juego, out(s)" id="34" type="X" code="X" tfs="201922" tfs_zulu="2016-03-13T20:19:22Z" x="109.20321584302326" y="156.44677734375" event_num="34" sz_top="3.46" sz_bot="1.56"  cc="" mt=""/></atbat><atbat num="7" b="0" s="0" o="1" start_tfs="201927" start_tfs_zulu="2016-03-13T20:19:27Z" end_tfs_zulu="2016-03-13T20:20:59Z" batter="543401" stand="L" b_height="5-11" pitcher="502624" p_throws="R" des="Jason Kipnis singles on a ground ball to third baseman Aaron Hill.  " des_es="Jason Kipnis pega sencillo con rodado a tercera base Aaron Hill.  " event_num="40" event="Single" event_es="Sencillo" home_team_runs="0" away_team_runs="2"><pitch des="In play, no out" des_es="En juego, no out" id="38" type="X" code="D" tfs="202052" tfs_zulu="2016-03-13T20:20:52Z" x="113.14807412790698" y="147.02294921874997" event_num="38" sz_top="3.26" sz_bot="1.48"  cc="" mt=""/><runner id="543401" start="" end="1B" event="Single" event_num="40"/></atbat><atbat num="8" b="0" s="0" o="1" start_tfs="202443" start_tfs_zulu="2016-03-13T20:24:43Z" end_tfs_zulu="2016-03-13T20:25:16Z" batter="596019" stand="L" b_height="5-11" pitcher="502624" p_throws="R" des="Francisco Lindor singles on a line drive to left fielder Keon Broxton.   Francisco Lindor to 2nd.  Jason Kipnis advances to 3rd, on a fielding error by left fielder Keon Broxton.  " des_es="Francisco Lindor pega sencillo con l&#237;nea a jardinero izquierdo Keon Broxton.   Francisco Lindor a 2da.  Jason Kipnis avanza a la 3ra, on error en en fildeo de jardinero izquierdo Keon Broxton.  " event_num="48" event="Single" event_es="Sencillo" event2="Error" event2_es="Error" home_team_runs="0" away_team_runs="2"><pitch des="In play, no out" des_es="En juego, no out" id="42" type="X" code="D" tfs="202451" tfs_zulu="2016-03-13T20:24:51Z" x="110.95648619186046" y="148.90771484375" event_num="42" on_1b="543401" sz_top="3.29" sz_bot="1.54"  cc="" mt=""/><runner id="543401" start="1B" end="3B" event="Single" event_num="48"/><runner id="596019" start="" end="2B" event="Single" event_num="48"/></atbat><atbat num="9" b="0" s="0" o="1" start_tfs="202521" start_tfs_zulu="2016-03-13T20:25:21Z" end_tfs_zulu="2016-03-13T20:25:32Z" batter="435063" stand="R" b_height="6-1" pitcher="502624" p_throws="R" des="Mike Napoli homers (2) on a fly ball to left center field.   Jason Kipnis scores.    Francisco Lindor scores.  " des_es="Mike Napoli batea jonr&#243;n (2) con elevado entre los jardines izquierdo y central.   Jason Kipnis anota  Francisco Lindor anota .  " event_num="57" event="Home Run" event_es="Jonr&#243;n" score="T" home_team_runs="3" away_team_runs="2"><pitch des="In play, run(s)" des_es="En juego, carrera(s)" id="50" type="X" code="E" tfs="202523" tfs_zulu="2016-03-13T20:25:23Z" x="112.7097565406977" y="147.02294921874997" event_num="50" on_2b="596019" on_3b="543401" sz_top="3.32" sz_bot="1.5"  cc="" mt=""/><runner id="596019" start="2B" end="" event="Home Run" event_num="57" score="T" rbi="T" earned="T"/><runner id="543401" start="3B" end="" event="Home Run" event_num="57" score="T" rbi="T" earned="T"/><runner id="435063" start="" end="" event="Home Run" event_num="57" score="T" rbi="T" earned="T"/></atbat><atbat num="10" b="0" s="0" o="1" start_tfs="202548" start_tfs_zulu="2016-03-13T20:25:48Z" end_tfs_zulu="2016-03-13T20:25:55Z" batter="543228" stand="R" b_height="6-2" pitcher="502624" p_throws="R" des="Yan Gomes homers (2) on a fly ball to left field.  " des_es="Yan Gomes batea jonr&#243;n (2) con elevado por el jard&#237;n izquierdo.  " event_num="62" event="Home Run" event_es="Jonr&#243;n" score="T" home_team_runs="4" away_team_runs="2"><pitch des="In play, run(s)" des_es="En juego, carrera(s)" id="59" type="X" code="E" tfs="202551" tfs_zulu="2016-03-13T20:25:51Z" x="106.57331031976744" y="138.54150390624997" event_num="59" sz_top="3.16" sz_bot="1.42"  cc="" mt=""/><runner id="543228" start="" end="" event="Home Run" event_num="62" score="T" rbi="T" earned="T"/></atbat><atbat num="11" b="0" s="0" o="2" start_tfs="202658" start_tfs_zulu="2016-03-13T20:26:58Z" end_tfs_zulu="2016-03-13T20:27:03Z" batter="461416" stand="L" b_height="6-3" pitcher="502624" p_throws="R" des="Will Venable flies out to center fielder Kirk Nieuwenhuis.  " des_es="Will Venable batea elevado de out a jardinero central Kirk Nieuwenhuis.  " event_num="66" event="Flyout" event_es="Elevado de Out" home_team_runs="4" away_team_runs="2"><pitch des="In play, out(s)" des_es="En juego, out(s)" id="64" type="X" code="X" tfs="202659" tfs_zulu="2016-03-13T20:26:59Z" x="119.28452034883723" y="121.10742187499999" event_num="64" sz_top="3.62" sz_bot="1.63"  cc="" mt=""/></atbat><atbat num="12" b="0" s="0" o="3" start_tfs="202747" start_tfs_zulu="2016-03-13T20:27:47Z" end_tfs_zulu="2016-03-13T20:27:52Z" batter="518577" stand="R" b_height="5-9" pitcher="502624" p_throws="R" des="Collin Cowgill flies out to right fielder Rymer Liriano.  " des_es="Collin Cowgill batea elevado de out a jardinero derecho Rymer Liriano.  " event_num="70" event="Flyout" event_es="Elevado de Out" home_team_runs="4" away_team_runs="2"><pitch des="In play, out(s)" des_es="En juego, out(s)" id="68" type="X" code="X" tfs="202749" tfs_zulu="2016-03-13T20:27:49Z" x="116.21629723837209" y="140.8974609375" event_num="68" sz_top="3.13" sz_bot="1.44"  cc="" mt=""/></atbat></bottom></inning><inning num="2" away_team="mil" home_team="cle" next="Y"><top><atbat num="13" b="0" s="0" o="0" start_tfs="203055" start_tfs_zulu="2016-03-13T20:30:55Z" end_tfs_zulu="2016-03-13T20:33:29Z" batter="519421" stand="L" b_height="6-1" pitcher="458708" p_throws="R" des="Andy Wilkins singles on a ground ball to third baseman Michael Martinez.  " des_es="Andy Wilkins pega sencillo con rodado a tercera base Michael Martinez.  " event_num="75" event="Single" event_es="Sencillo" home_team_runs="4" away_team_runs="2"><pitch des="In play, no out" des_es="En juego, no out" id="73" type="X" code="D" tfs="203057" tfs_zulu="2016-03-13T20:30:57Z" x="112.27143895348837" y="135.2431640625" event_num="73" sz_top="3.31" sz_bot="1.5"  cc="" mt=""/><runner id="519421" start="" end="1B" event="Single" event_num="75"/></atbat><atbat num="14" b="0" s="3" o="1" start_tfs="203330" start_tfs_zulu="2016-03-13T20:33:30Z" end_tfs_zulu="2016-03-13T20:33:35Z" batter="542340" stand="L" b_height="6-1" pitcher="458708" p_throws="R" des="Jonathan Villar strikes out swinging.  " des_es="Jonathan Villar se poncha tir&#225;ndole.  " event_num="81" event="Strikeout" event_es="Ponche" home_team_runs="4" away_team_runs="2"><pitch des="Swinging Strike" des_es="Strike tir&#225;ndole" id="77" type="S" code="S" tfs="203332" tfs_zulu="2016-03-13T20:33:32Z" x="104.38172238372093" y="136.65673828124997" event_num="77" on_1b="519421" sz_top="3.411" sz_bot="1.565"  cc="" mt=""/><pitch des="Swinging Strike" des_es="Strike tir&#225;ndole" id="78" type="S" code="S" tfs="203332" tfs_zulu="2016-03-13T20:33:32Z" x="107.01162790697674" y="127.23291015624999" event_num="78" on_1b="519421" sz_top="3.411" sz_bot="1.565"  cc="" mt=""/><pitch des="Swinging Strike" des_es="Strike tir&#225;ndole" id="79" type="S" code="S" tfs="203334" tfs_zulu="2016-03-13T20:33:34Z" x="107.01162790697674" y="127.23291015624999" event_num="79" on_1b="519421" sz_top="3.411" sz_bot="1.565"  cc="" mt=""/></atbat><atbat num="15" b="0" s="3" o="2" start_tfs="203522" start_tfs_zulu="2016-03-13T20:35:22Z" end_tfs_zulu="2016-03-13T20:35:26Z" batter="455117" stand="R" b_height="6-0" pitcher="458708" p_throws="R" des="Martin Maldonado strikes out swinging.  " des_es="Martin Maldonado se poncha tir&#225;ndole.  " event_num="87" event="Strikeout" event_es="Ponche" home_team_runs="4" away_team_runs="2"><pitch des="Swinging Strike" des_es="Strike tir&#225;ndole" id="83" type="S" code="S" tfs="203523" tfs_zulu="2016-03-13T20:35:23Z" x="112.27143895348837" y="132.88720703125" event_num="83" on_1b="519421" sz_top="3.4" sz_bot="1.49"  cc="" mt=""/><pitch des="Swinging Strike" des_es="Strike tir&#225;ndole" id="84" type="S" code="S" tfs="203524" tfs_zulu="2016-03-13T20:35:24Z" x="112.27143895348837" y="132.88720703125" event_num="84" on_1b="519421" sz_top="3.4" sz_bot="1.49"  cc="" mt=""/><pitch des="Swinging Strike" des_es="Strike tir&#225;ndole" id="85" type="S" code="S" tfs="203525" tfs_zulu="2016-03-13T20:35:25Z" x="112.27143895348837" y="132.88720703125" event_num="85" on_1b="519421" sz_top="3.4" sz_bot="1.49"  cc="" mt=""/></atbat><atbat num="16" b="0" s="0" o="3" start_tfs="203656" start_tfs_zulu="2016-03-13T20:36:56Z" end_tfs_zulu="2016-03-13T20:37:15Z" batter="592680" stand="R" b_height="6-3" pitcher="458708" p_throws="R" des="Yadiel Rivera grounds into a force out, shortstop Francisco Lindor to second baseman Jason Kipnis.   Andy Wilkins out at 2nd.  " des_es="Yadiel Rivera batea rodado batea para out forzado, campo corto Francisco Lindor a segunda base Jason Kipnis.   Andy Wilkins a cabo a 2da.  " event_num="92" event="Forceout" event_es="Out Forzado" home_team_runs="4" away_team_runs="2"><pitch des="In play, out(s)" des_es="En juego, out(s)" id="89" type="X" code="X" tfs="203701" tfs_zulu="2016-03-13T20:37:01Z" x="114.90134447674419" y="141.83984374999997" event_num="89" on_1b="519421" sz_top="3.54" sz_bot="1.61"  cc="" mt=""/><runner id="519421" start="1B" end="" event="Forceout" event_num="92"/></atbat></top><bottom><atbat num="17" b="0" s="0" o="1" start_tfs="204024" start_tfs_zulu="2016-03-13T20:40:24Z" end_tfs_zulu="2016-03-13T20:40:29Z" batter="542994" stand="R" b_height="6-2" pitcher="502624" p_throws="R" des="Joey Butler flies out to right fielder Rymer Liriano.  " des_es="Joey Butler batea elevado de out a jardinero derecho Rymer Liriano.  " event_num="98" event="Flyout" event_es="Elevado de Out" home_team_runs="4" away_team_runs="2"><pitch des="In play, out(s)" des_es="En juego, out(s)" id="96" type="X" code="X" tfs="204026" tfs_zulu="2016-03-13T20:40:26Z" x="103.06676962209302" y="130.53124999999997" event_num="96" sz_top="3.54" sz_bot="1.72"  cc="" mt=""/></atbat><atbat num="18" b="0" s="3" o="2" start_tfs="204029" start_tfs_zulu="2016-03-13T20:40:29Z" end_tfs_zulu="2016-03-13T20:40:32Z" batter="492841" stand="L" b_height="5-9" pitcher="502624" p_throws="R" des="Michael Martinez strikes out swinging.  " des_es="Michael Martinez se poncha tir&#225;ndole.  " event_num="104" event="Strikeout" event_es="Ponche" home_team_runs="4" away_team_runs="2"><pitch des="Swinging Strike" des_es="Strike tir&#225;ndole" id="100" type="S" code="S" tfs="204030" tfs_zulu="2016-03-13T20:40:30Z" x="117.96956758720933" y="147.49414062499997" event_num="100" sz_top="3.21" sz_bot="1.51"  cc="" mt=""/><pitch des="Swinging Strike" des_es="Strike tir&#225;ndole" id="101" type="S" code="S" tfs="204031" tfs_zulu="2016-03-13T20:40:31Z" x="117.96956758720933" y="147.49414062499997" event_num="101" sz_top="3.21" sz_bot="1.51"  cc="" mt=""/><pitch des="Swinging Strike" des_es="Strike tir&#225;ndole" id="102" type="S" code="S" tfs="204032" tfs_zulu="2016-03-13T20:40:32Z" x="117.96956758720933" y="147.49414062499997" event_num="102" sz_top="3.21" sz_bot="1.51"  cc="" mt=""/></atbat><atbat num="19" b="0" s="0" o="3" start_tfs="204110" start_tfs_zulu="2016-03-13T20:41:10Z" end_tfs_zulu="2016-03-13T20:41:16Z" batter="434658" stand="R" b_height="5-10" pitcher="502624" p_throws="R" des="Rajai Davis pops out to shortstop Jonathan Villar.  " des_es="Rajai Davis batea elevadito de out a campo corto Jonathan Villar.  " event_num="108" event="Pop Out" event_es="Elevado de Out" home_team_runs="4" away_team_runs="2"><pitch des="In play, out(s)" des_es="En juego, out(s)" id="106" type="X" code="X" tfs="204112" tfs_zulu="2016-03-13T20:41:12Z" x="110.95648619186046" y="147.96533203125" event_num="106" sz_top="3.46" sz_bot="1.56"  cc="" mt=""/></atbat></bottom></inning><inning num="3" away_team="mil" home_team="cle" next="Y"><top><atbat num="20" b="0" s="0" o="1" start_tfs="204518" start_tfs_zulu="2016-03-13T20:45:18Z" end_tfs_zulu="2016-03-13T20:45:23Z" batter="542979" stand="R" b_height="6-3" pitcher="458708" p_throws="R" des="Keon Broxton flies out to center fielder Rajai Davis.  " des_es="Keon Broxton batea elevado de out a jardinero central Rajai Davis.  " event_num="113" event="Flyout" event_es="Elevado de Out" home_team_runs="4" away_team_runs="2"><pitch des="In play, out(s)" des_es="En juego, out(s)" id="111" type="X" code="X" tfs="204520" tfs_zulu="2016-03-13T20:45:20Z" x="107.01162790697674" y="132.416015625" event_num="111" sz_top="3.61" sz_bot="1.62"  cc="" mt=""/></atbat><atbat num="21" b="0" s="0" o="2" start_tfs="204625" start_tfs_zulu="2016-03-13T20:46:25Z" end_tfs_zulu="2016-03-13T20:46:30Z" batter="518960" stand="R" b_height="6-0" pitcher="458708" p_throws="R" des="Jonathan Lucroy flies out to right fielder Collin Cowgill.  " des_es="Jonathan Lucroy batea elevado de out a jardinero derecho Collin Cowgill.  " event_num="117" event="Flyout" event_es="Elevado de Out" home_team_runs="4" away_team_runs="2"><pitch des="In play, out(s)" des_es="En juego, out(s)" id="115" type="X" code="X" tfs="204627" tfs_zulu="2016-03-13T20:46:27Z" x="98.24527616279072" y="138.54150390624997" event_num="115" sz_top="3.51" sz_bot="1.51"  cc="" mt=""/></atbat><atbat num="22" b="0" s="0" o="3" start_tfs="204707" start_tfs_zulu="2016-03-13T20:47:07Z" end_tfs_zulu="2016-03-13T20:47:16Z" batter="431094" stand="R" b_height="5-11" pitcher="458708" p_throws="R" des="Aaron Hill grounds out, second baseman Jason Kipnis to first baseman Mike Napoli.  " des_es="Aaron Hill batea rodado de out, segunda base Jason Kipnis a primera base Mike Napoli.  " event_num="121" event="Groundout" event_es="Roletazo de Out" home_team_runs="4" away_team_runs="2"><pitch des="In play, out(s)" des_es="En juego, out(s)" id="119" type="X" code="X" tfs="204711" tfs_zulu="2016-03-13T20:47:11Z" x="110.95648619186046" y="138.54150390624997" event_num="119" sz_top="3.32" sz_bot="1.45"  cc="" mt=""/></atbat></top><bottom><atbat num="23" b="0" s="0" o="1" start_tfs="204936" start_tfs_zulu="2016-03-13T20:49:36Z" end_tfs_zulu="2016-03-13T20:49:42Z" batter="543401" stand="L" b_height="5-11" pitcher="502624" p_throws="R" des="Jason Kipnis pops out to shortstop Jonathan Villar.  " des_es="Jason Kipnis batea elevadito de out a campo corto Jonathan Villar.  " event_num="126" event="Pop Out" event_es="Elevado de Out" home_team_runs="4" away_team_runs="2"><pitch des="In play, out(s)" des_es="En juego, out(s)" id="124" type="X" code="X" tfs="204938" tfs_zulu="2016-03-13T20:49:38Z" x="109.20321584302326" y="144.66699218749997" event_num="124" sz_top="3.26" sz_bot="1.48"  cc="" mt=""/></atbat><atbat num="24" b="0" s="0" o="2" start_tfs="204943" start_tfs_zulu="2016-03-13T20:49:43Z" end_tfs_zulu="2016-03-13T20:51:11Z" batter="596019" stand="L" b_height="5-11" pitcher="502624" p_throws="R" des="Francisco Lindor flies out to center fielder Kirk Nieuwenhuis.  " des_es="Francisco Lindor batea elevado de out a jardinero central Kirk Nieuwenhuis.  " event_num="130" event="Flyout" event_es="Elevado de Out" home_team_runs="4" away_team_runs="2"><pitch des="In play, out(s)" des_es="En juego, out(s)" id="128" type="X" code="X" tfs="205107" tfs_zulu="2016-03-13T20:51:07Z" x="104.38172238372093" y="151.263671875" event_num="128" sz_top="3.29" sz_bot="1.54"  cc="" mt=""/></atbat><atbat num="25" b="0" s="0" o="2" start_tfs="205306" start_tfs_zulu="2016-03-13T20:53:06Z" end_tfs_zulu="2016-03-13T20:53:14Z" batter="435063" stand="R" b_height="6-1" pitcher="502624" p_throws="R" des="Mike Napoli singles on a line drive to right fielder Rymer Liriano.  " des_es="Mike Napoli pega sencillo con l&#237;nea a jardinero derecho Rymer Liriano.  " event_num="134" event="Single" event_es="Sencillo" home_team_runs="4" away_team_runs="2"><pitch des="In play, no out" des_es="En juego, no out" id="132" type="X" code="D" tfs="205309" tfs_zulu="2016-03-13T20:53:09Z" x="112.27143895348837" y="158.802734375" event_num="132" sz_top="3.32" sz_bot="1.5"  cc="" mt=""/><runner id="435063" start="" end="1B" event="Single" event_num="134"/></atbat><atbat num="26" b="0" s="0" o="3" start_tfs="205436" start_tfs_zulu="2016-03-13T20:54:36Z" end_tfs_zulu="2016-03-13T20:54:46Z" batter="543228" stand="R" b_height="6-2" pitcher="502624" p_throws="R" des="Yan Gomes grounds into a force out, shortstop Jonathan Villar to second baseman Yadiel Rivera.   Mike Napoli out at 2nd.  " des_es="Yan Gomes batea rodado batea para out forzado, campo corto Jonathan Villar a segunda base Yadiel Rivera.   Mike Napoli a cabo a 2da.  " event_num="139" event="Forceout" event_es="Out Forzado" home_team_runs="4" away_team_runs="2"><pitch des="In play, out(s)" des_es="En juego, out(s)" id="136" type="X" code="X" tfs="205438" tfs_zulu="2016-03-13T20:54:38Z" x="124.98264898255815" y="138.0703125" event_num="136" on_1b="435063" sz_top="3.16" sz_bot="1.42"  cc="" mt=""/><runner id="435063" start="1B" end="" event="Forceout" event_num="139"/></atbat></bottom></inning><inning num="4" away_team="mil" home_team="cle" next="Y"><top><action b="0" s="0" o="0" des="Pitching Change: Bryan Shaw replaces Josh Tomlin.  " des_es="Cambio de Lanzador: Bryan Shaw reemplaza a Josh Tomlin.  " event="Pitching Substitution" event_es="Cambio de Lanzador" tfs="205518" tfs_zulu="2016-03-13T20:55:18Z" player="543766" pitch="1" event_num="143" home_team_runs="4" away_team_runs="2"/><atbat num="27" b="0" s="0" o="1" start_tfs="205800" start_tfs_zulu="2016-03-13T20:58:00Z" end_tfs_zulu="2016-03-13T20:58:08Z" batter="543590" stand="L" b_height="6-3" pitcher="543766" p_throws="R" des="Kirk Nieuwenhuis grounds out, shortstop Francisco Lindor to first baseman Mike Napoli.  " des_es="Kirk Nieuwenhuis batea rodado de out, campo corto Francisco Lindor a primera base Mike Napoli.  " event_num="147" event="Groundout" event_es="Roletazo de Out" home_team_runs="4" away_team_runs="2"><pitch des="In play, out(s)" des_es="En juego, out(s)" id="145" type="X" code="X" tfs="205802" tfs_zulu="2016-03-13T20:58:02Z" x="107.01162790697674" y="144.19580078124997" event_num="145" sz_top="3.38" sz_bot="1.58"  cc="" mt=""/></atbat><atbat num="28" b="0" s="0" o="2" start_tfs="205809" start_tfs_zulu="2016-03-13T20:58:09Z" end_tfs_zulu="2016-03-13T20:59:20Z" batter="542642" stand="R" b_height="6-0" pitcher="543766" p_throws="R" des="Rymer Liriano flies out to left fielder Joey Butler.  " des_es="Rymer Liriano batea elevado de out a jardinero izquierdo Joey Butler.  " event_num="151" event="Flyout" event_es="Elevado de Out" home_team_runs="4" away_team_runs="2"><pitch des="In play, out(s)" des_es="En juego, out(s)" id="149" type="X" code="X" tfs="205917" tfs_zulu="2016-03-13T20:59:17Z" x="99.56022892441862" y="145.609375" event_num="149" sz_top="3.4" sz_bot="1.52"  cc="" mt=""/></atbat><atbat num="29" b="4" s="0" o="2" start_tfs="210122" start_tfs_zulu="2016-03-13T21:01:22Z" end_tfs_zulu="2016-03-13T21:01:25Z" batter="519421" stand="L" b_height="6-1" pitcher="543766" p_throws="R" des="Andy Wilkins walks.  " des_es="Andy Wilkins recibe base por bolas.  " event_num="158" event="Walk" event_es="Base por Bolas" home_team_runs="4" away_team_runs="2"><pitch des="Ball" des_es="Bola mala" id="153" type="B" code="B" tfs="210122" tfs_zulu="2016-03-13T21:01:22Z" x="104.82003997093025" y="91.89355468749999" event_num="153" sz_top="3.31" sz_bot="1.5"  cc="" mt=""/><pitch des="Ball" des_es="Bola mala" id="154" type="B" code="B" tfs="210123" tfs_zulu="2016-03-13T21:01:23Z" x="104.82003997093025" y="91.89355468749999" event_num="154" sz_top="3.31" sz_bot="1.5"  cc="" mt=""/><pitch des="Ball" des_es="Bola mala" id="155" type="B" code="B" tfs="210123" tfs_zulu="2016-03-13T21:01:23Z" x="104.82003997093025" y="91.89355468749999" event_num="155" sz_top="3.31" sz_bot="1.5"  cc="" mt=""/><pitch des="Ball" des_es="Bola mala" id="156" type="B" code="B" tfs="210124" tfs_zulu="2016-03-13T21:01:24Z" x="104.82003997093025" y="91.89355468749999" event_num="156" sz_top="3.31" sz_bot="1.5"  cc="" mt=""/><runner id="519421" start="" end="1B" event="Walk" event_num="158"/></atbat><atbat num="30" b="0" s="0" o="3" start_tfs="210248" start_tfs_zulu="2016-03-13T21:02:48Z" end_tfs_zulu="2016-03-13T21:02:54Z" batter="542340" stand="L" b_height="6-1" pitcher="543766" p_throws="R" des="Jonathan Villar grounds out, pitcher Bryan Shaw to first baseman Mike Napoli.  " des_es="Jonathan Villar batea rodado de out, lanzador Bryan Shaw a primera base Mike Napoli.  " event_num="162" event="Groundout" event_es="Roletazo de Out" home_team_runs="4" away_team_runs="2"><pitch des="In play, out(s)" des_es="En juego, out(s)" id="160" type="X" code="X" tfs="210250" tfs_zulu="2016-03-13T21:02:50Z" x="109.20321584302326" y="131.94482421875" event_num="160" on_1b="519421" sz_top="3.411" sz_bot="1.565"  cc="" mt=""/><runner id="519421" start="1B" end="" event="Groundout" event_num="162"/></atbat></top><bottom><action b="0" s="0" o="0" des="Pitching Change: Zach Davies replaces Chase Anderson.  " des_es="Cambio de Lanzador: Zach Davies reemplaza a Chase Anderson.  " event="Pitching Substitution" event_es="Cambio de Lanzador" tfs="210331" tfs_zulu="2016-03-13T21:03:31Z" player="605200" pitch="1" event_num="166" home_team_runs="4" away_team_runs="2"/><atbat num="31" b="0" s="0" o="1" start_tfs="210655" start_tfs_zulu="2016-03-13T21:06:55Z" end_tfs_zulu="2016-03-13T21:07:00Z" batter="461416" stand="L" b_height="6-3" pitcher="605200" p_throws="R" des="Will Venable flies out to left fielder Keon Broxton.  " des_es="Will Venable batea elevado de out a jardinero izquierdo Keon Broxton.  " event_num="170" event="Flyout" event_es="Elevado de Out" home_team_runs="4" away_team_runs="2"><pitch des="In play, out(s)" des_es="En juego, out(s)" id="168" type="X" code="X" tfs="210657" tfs_zulu="2016-03-13T21:06:57Z" x="110.51816860465117" y="122.52099609374997" event_num="168" sz_top="3.62" sz_bot="1.63"  cc="" mt=""/></atbat><atbat num="32" b="0" s="3" o="2" start_tfs="210701" start_tfs_zulu="2016-03-13T21:07:01Z" end_tfs_zulu="2016-03-13T21:08:19Z" batter="518577" stand="R" b_height="5-9" pitcher="605200" p_throws="R" des="Collin Cowgill strikes out swinging.  " des_es="Collin Cowgill se poncha tir&#225;ndole.  " event_num="176" event="Strikeout" event_es="Ponche" home_team_runs="4" away_team_runs="2"><pitch des="Swinging Strike" des_es="Strike tir&#225;ndole" id="172" type="S" code="S" tfs="210817" tfs_zulu="2016-03-13T21:08:17Z" x="92.10882994186046" y="163.51464843749997" event_num="172" sz_top="3.13" sz_bot="1.44"  cc="" mt=""/><pitch des="Swinging Strike" des_es="Strike tir&#225;ndole" id="173" type="S" code="S" tfs="210817" tfs_zulu="2016-03-13T21:08:17Z" x="92.10882994186046" y="163.51464843749997" event_num="173" sz_top="3.13" sz_bot="1.44"  cc="" mt=""/><pitch des="Swinging Strike" des_es="Strike tir&#225;ndole" id="174" type="S" code="S" tfs="210819" tfs_zulu="2016-03-13T21:08:19Z" x="92.10882994186046" y="163.51464843749997" event_num="174" sz_top="3.13" sz_bot="1.44"  cc="" mt=""/></atbat><atbat num="33" b="0" s="0" o="3" start_tfs="210942" start_tfs_zulu="2016-03-13T21:09:42Z" end_tfs_zulu="2016-03-13T21:09:48Z" batter="542994" stand="R" b_height="6-2" pitcher="605200" p_throws="R" des="Joey Butler flies out to right fielder Rymer Liriano.  " des_es="Joey Butler batea elevado de out a jardinero derecho Rymer Liriano.  " event_num="180" event="Flyout" event_es="Elevado de Out" home_team_runs="4" away_team_runs="2"><pitch des="In play, out(s)" des_es="En juego, out(s)" id="178" type="X" code="X" tfs="210945" tfs_zulu="2016-03-13T21:09:45Z" x="107.44994549418607" y="142.31103515625" event_num="178" sz_top="3.54" sz_bot="1.72"  cc="" mt=""/></atbat></bottom></inning><inning num="5" away_team="mil" home_team="cle" next="Y"><top><action b="0" s="0" o="0" des="Pitching Change: Joba Chamberlain replaces Bryan Shaw.  " des_es="Cambio de Lanzador: Joba Chamberlain reemplaza a Bryan Shaw.  " event="Pitching Substitution" event_es="Cambio de Lanzador" tfs="211051" tfs_zulu="2016-03-13T21:10:51Z" player="501955" pitch="1" event_num="183" home_team_runs="4" away_team_runs="2"/><atbat num="34" b="0" s="0" o="0" start_tfs="211325" start_tfs_zulu="2016-03-13T21:13:25Z" end_tfs_zulu="2016-03-13T21:13:35Z" batter="455117" stand="R" b_height="6-0" pitcher="501955" p_throws="R" des="Martin Maldonado triples (1) on a fly ball to center fielder Rajai Davis.  " des_es="Martin Maldonado pega triple (1) con elevado al jardinero central Rajai Davis.  " event_num="187" event="Triple" event_es="Triple" home_team_runs="4" away_team_runs="2"><pitch des="In play, no out" des_es="En juego, no out" id="185" type="X" code="D" tfs="211328" tfs_zulu="2016-03-13T21:13:28Z" x="103.94340479651163" y="147.49414062499997" event_num="185" sz_top="3.4" sz_bot="1.49"  cc="" mt=""/><runner id="455117" start="" end="3B" event="Triple" event_num="187"/></atbat><atbat num="35" b="0" s="3" o="1" start_tfs="211418" start_tfs_zulu="2016-03-13T21:14:18Z" end_tfs_zulu="2016-03-13T21:14:22Z" batter="592680" stand="R" b_height="6-3" pitcher="501955" p_throws="R" des="Yadiel Rivera strikes out swinging.  " des_es="Yadiel Rivera se poncha tir&#225;ndole.  " event_num="193" event="Strikeout" event_es="Ponche" home_team_runs="4" away_team_runs="2"><pitch des="Swinging Strike" des_es="Strike tir&#225;ndole" id="189" type="S" code="S" tfs="211420" tfs_zulu="2016-03-13T21:14:20Z" x="127.61255450581396" y="127.23291015624999" event_num="189" on_3b="455117" sz_top="3.54" sz_bot="1.61"  cc="" mt=""/><pitch des="Swinging Strike" des_es="Strike tir&#225;ndole" id="190" type="S" code="S" tfs="211420" tfs_zulu="2016-03-13T21:14:20Z" x="129.80414244186048" y="126.76171874999999" event_num="190" on_3b="455117" sz_top="3.54" sz_bot="1.61"  cc="" mt=""/><pitch des="Swinging Strike" des_es="Strike tir&#225;ndole" id="191" type="S" code="S" tfs="211421" tfs_zulu="2016-03-13T21:14:21Z" x="129.80414244186048" y="126.76171874999999" event_num="191" on_3b="455117" sz_top="3.54" sz_bot="1.61"  cc="" mt=""/></atbat><atbat num="36" b="0" s="3" o="2" start_tfs="211714" start_tfs_zulu="2016-03-13T21:17:14Z" end_tfs_zulu="2016-03-13T21:19:04Z" batter="542979" stand="R" b_height="6-3" pitcher="501955" p_throws="R" des="Keon Broxton strikes out swinging.  " des_es="Keon Broxton se poncha tir&#225;ndole.  " event_num="199" event="Strikeout" event_es="Ponche" home_team_runs="4" away_team_runs="2"><pitch des="Swinging Strike" des_es="Strike tir&#225;ndole" id="195" type="S" code="S" tfs="211714" tfs_zulu="2016-03-13T21:17:14Z" x="110.07985101744188" y="125.81933593749997" event_num="195" on_3b="455117" sz_top="3.61" sz_bot="1.62"  cc="" mt=""/><pitch des="Swinging Strike" des_es="Strike tir&#225;ndole" id="196" type="S" code="S" tfs="211715" tfs_zulu="2016-03-13T21:17:15Z" x="110.07985101744188" y="125.81933593749997" event_num="196" on_3b="455117" sz_top="3.61" sz_bot="1.62"  cc="" mt=""/><pitch des="Swinging Strike" des_es="Strike tir&#225;ndole" id="197" type="S" code="S" tfs="211716" tfs_zulu="2016-03-13T21:17:16Z" x="110.07985101744188" y="125.81933593749997" event_num="197" on_3b="455117" sz_top="3.61" sz_bot="1.62"  cc="" mt=""/></atbat><atbat num="37" b="0" s="0" o="3" start_tfs="211905" start_tfs_zulu="2016-03-13T21:19:05Z" end_tfs_zulu="2016-03-13T21:19:10Z" batter="518960" stand="R" b_height="6-0" pitcher="501955" p_throws="R" des="Jonathan Lucroy lines out to second baseman Jason Kipnis.  " des_es="Jonathan Lucroy batea l&#237;nea de out a segunda base Jason Kipnis.  " event_num="203" event="Lineout" event_es="Línea de Out" home_team_runs="4" away_team_runs="2"><pitch des="In play, out(s)" des_es="En juego, out(s)" id="201" type="X" code="X" tfs="211907" tfs_zulu="2016-03-13T21:19:07Z" x="122.79106104651163" y="123.46337890624999" event_num="201" on_3b="455117" sz_top="3.51" sz_bot="1.51"  cc="" mt=""/><runner id="455117" start="3B" end="" event="Lineout" event_num="203"/></atbat></top><bottom><atbat num="38" b="0" s="0" o="1" start_tfs="212134" start_tfs_zulu="2016-03-13T21:21:34Z" end_tfs_zulu="2016-03-13T21:21:39Z" batter="492841" stand="L" b_height="5-9" pitcher="605200" p_throws="R" des="Michael Martinez grounds out, shortstop Jonathan Villar to first baseman Andy Wilkins.  " des_es="Michael Martinez batea rodado de out, campo corto Jonathan Villar a primera base Andy Wilkins.  " event_num="209" event="Groundout" event_es="Roletazo de Out" home_team_runs="4" away_team_runs="2"><pitch des="In play, out(s)" des_es="En juego, out(s)" id="207" type="X" code="X" tfs="212135" tfs_zulu="2016-03-13T21:21:35Z" x="104.82003997093025" y="140.42626953125" event_num="207" sz_top="3.21" sz_bot="1.51"  cc="" mt=""/></atbat><atbat num="39" b="0" s="0" o="2" start_tfs="212225" start_tfs_zulu="2016-03-13T21:22:25Z" end_tfs_zulu="2016-03-13T21:22:31Z" batter="434658" stand="R" b_height="5-10" pitcher="605200" p_throws="R" des="Rajai Davis grounds out, third baseman Aaron Hill to first baseman Andy Wilkins.  " des_es="Rajai Davis batea rodado de out, tercera base Aaron Hill a primera base Andy Wilkins.  " event_num="213" event="Groundout" event_es="Roletazo de Out" home_team_runs="4" away_team_runs="2"><pitch des="In play, out(s)" des_es="En juego, out(s)" id="211" type="X" code="X" tfs="212227" tfs_zulu="2016-03-13T21:22:27Z" x="98.24527616279072" y="159.7451171875" event_num="211" sz_top="3.46" sz_bot="1.56"  cc="" mt=""/></atbat><atbat num="40" b="0" s="0" o="3" start_tfs="212343" start_tfs_zulu="2016-03-13T21:23:43Z" end_tfs_zulu="2016-03-13T21:23:49Z" batter="543401" stand="L" b_height="5-11" pitcher="605200" p_throws="R" des="Jason Kipnis grounds out, second baseman Yadiel Rivera to first baseman Andy Wilkins.  " des_es="Jason Kipnis batea rodado de out, segunda base Yadiel Rivera a primera base Andy Wilkins.  " event_num="217" event="Groundout" event_es="Roletazo de Out" home_team_runs="4" away_team_runs="2"><pitch des="In play, out(s)" des_es="En juego, out(s)" id="215" type="X" code="X" tfs="212345" tfs_zulu="2016-03-13T21:23:45Z" x="100.87518168604653" y="153.14843749999997" event_num="215" sz_top="3.26" sz_bot="1.48"  cc="" mt=""/></atbat></bottom></inning><inning num="6" away_team="mil" home_team="cle" next="Y"><top><action b="0" s="0" o="0" des="Pitching Change: Will Roberts replaces Joba Chamberlain.  " des_es="Cambio de Lanzador: Will Roberts reemplaza a Joba Chamberlain.  " event="Pitching Substitution" event_es="Cambio de Lanzador" tfs="212418" tfs_zulu="2016-03-13T21:24:18Z" player="543704" pitch="1" event_num="220" home_team_runs="4" away_team_runs="2"/><action b="0" s="0" o="0" des="Defensive Substitution: Zach Walters replaces center fielder Rajai Davis, batting 1st, playing right field.  " des_es="Sustituci&#243;n a la Defensiva: Zach Walters reemplaza a jardinero central Rajai Davis, como primer bate y jugando en el jardinero derecho.  " event="Defensive Sub" event_es="Sustituci&#243;n Defensiva" tfs="212619" tfs_zulu="2016-03-13T21:26:19Z" player="595025" pitch="1" event_num="222" home_team_runs="4" away_team_runs="2"/><action b="0" s="0" o="0" des="Defensive switch from right field to center field for Collin Cowgill.  " des_es="Sustituci&#243;n a la defensiva de jardinero derecho a jardinero central por Collin Cowgill.  " event="Defensive Switch" event_es="Cambio Defensivo" tfs="212619" tfs_zulu="2016-03-13T21:26:19Z" player="518577" pitch="1" event_num="224" home_team_runs="4" away_team_runs="2"/><atbat num="41" b="0" s="0" o="1" start_tfs="212625" start_tfs_zulu="2016-03-13T21:26:25Z" end_tfs_zulu="2016-03-13T21:26:30Z" batter="431094" stand="R" b_height="5-11" pitcher="543704" p_throws="R" des="Aaron Hill flies out to left fielder Joey Butler.  " des_es="Aaron Hill batea elevado de out a jardinero izquierdo Joey Butler.  " event_num="228" event="Flyout" event_es="Elevado de Out" home_team_runs="4" away_team_runs="2"><pitch des="In play, out(s)" des_es="En juego, out(s)" id="226" type="X" code="X" tfs="212626" tfs_zulu="2016-03-13T21:26:26Z" x="112.7097565406977" y="131.4736328125" event_num="226" sz_top="3.32" sz_bot="1.45"  cc="" mt=""/></atbat><atbat num="42" b="4" s="0" o="1" start_tfs="212827" start_tfs_zulu="2016-03-13T21:28:27Z" end_tfs_zulu="2016-03-13T21:28:32Z" batter="543590" stand="L" b_height="6-3" pitcher="543704" p_throws="R" des="Kirk Nieuwenhuis walks.  " des_es="Kirk Nieuwenhuis recibe base por bolas.  " event_num="235" event="Walk" event_es="Base por Bolas" home_team_runs="4" away_team_runs="2"><pitch des="Ball" des_es="Bola mala" id="230" type="B" code="B" tfs="212829" tfs_zulu="2016-03-13T21:28:29Z" x="132.4340479651163" y="73.51708984374999" event_num="230" sz_top="3.38" sz_bot="1.58"  cc="" mt=""/><pitch des="Ball" des_es="Bola mala" id="231" type="B" code="B" tfs="212829" tfs_zulu="2016-03-13T21:28:29Z" x="132.4340479651163" y="73.51708984374999" event_num="231" sz_top="3.38" sz_bot="1.58"  cc="" mt=""/><pitch des="Ball" des_es="Bola mala" id="232" type="B" code="B" tfs="212830" tfs_zulu="2016-03-13T21:28:30Z" x="132.4340479651163" y="73.51708984374999" event_num="232" sz_top="3.38" sz_bot="1.58"  cc="" mt=""/><pitch des="Ball" des_es="Bola mala" id="233" type="B" code="B" tfs="212831" tfs_zulu="2016-03-13T21:28:31Z" x="132.4340479651163" y="73.51708984374999" event_num="233" sz_top="3.38" sz_bot="1.58"  cc="" mt=""/><runner id="543590" start="" end="1B" event="Walk" event_num="235"/></atbat><action b="0" s="1" o="1" des="With Rymer Liriano batting, throwing error by Yan Gomes on the pickoff attempt, Kirk Nieuwenhuis to 2nd.  " des_es="Con Rymer Liriano bateando, error en tiro de Yan Gomes en el intent de viraje, Kirk Nieuwenhuis a 2da.  " event="Pickoff Error 1B" event_es="Error en Viraje a 1B" tfs="213141" tfs_zulu="2016-03-13T21:31:41Z" player="543590" pitch="1" event_num="241" home_team_runs="4" away_team_runs="2"/><atbat num="43" b="0" s="3" o="2" start_tfs="213051" start_tfs_zulu="2016-03-13T21:30:51Z" end_tfs_zulu="2016-03-13T21:31:49Z" batter="542642" stand="R" b_height="6-0" pitcher="543704" p_throws="R" des="Rymer Liriano strikes out swinging.  " des_es="Rymer Liriano se poncha tir&#225;ndole.  " event_num="245" event="Strikeout" event_es="Ponche" home_team_runs="4" away_team_runs="2"><pitch des="Swinging Strike" des_es="Strike tir&#225;ndole" id="237" type="S" code="S" tfs="213122" tfs_zulu="2016-03-13T21:31:22Z" x="107.44994549418607" y="147.96533203125" event_num="237" on_1b="543590" sz_top="3.4" sz_bot="1.52"  cc="" mt=""/><po des="Pickoff Attempt 1B"  des_es="Viraje a 1B" event_num="238" catcher="true" /><po des="Pickoff Error 1B"  des_es="Error en Viraje a 1B" event_num="239" /><runner id="543590" start="1B" end="2B" event="Pickoff Error 1B" event_num="241"/><pitch des="Swinging Strike" des_es="Strike tir&#225;ndole" id="242" type="S" code="S" tfs="213146" tfs_zulu="2016-03-13T21:31:46Z" x="107.01162790697674" y="151.73486328125" event_num="242" on_2b="543590" sz_top="3.4" sz_bot="1.52"  cc="" mt=""/><pitch des="Swinging Strike" des_es="Strike tir&#225;ndole" id="243" type="S" code="S" tfs="213148" tfs_zulu="2016-03-13T21:31:48Z" x="107.01162790697674" y="151.73486328125" event_num="243" on_2b="543590" sz_top="3.4" sz_bot="1.52"  cc="" mt=""/></atbat><atbat num="44" b="0" s="0" o="3" start_tfs="213315" start_tfs_zulu="2016-03-13T21:33:15Z" end_tfs_zulu="2016-03-13T21:33:21Z" batter="519421" stand="L" b_height="6-1" pitcher="543704" p_throws="R" des="Andy Wilkins flies out to left fielder Joey Butler.  " des_es="Andy Wilkins batea elevado de out a jardinero izquierdo Joey Butler.  " event_num="249" event="Flyout" event_es="Elevado de Out" home_team_runs="4" away_team_runs="2"><pitch des="In play, out(s)" des_es="En juego, out(s)" id="247" type="X" code="X" tfs="213317" tfs_zulu="2016-03-13T21:33:17Z" x="109.20321584302326" y="143.25341796875" event_num="247" on_2b="543590" sz_top="3.31" sz_bot="1.5"  cc="" mt=""/><runner id="543590" start="2B" end="" event="Flyout" event_num="249"/></atbat></top><bottom><action b="0" s="0" o="0" des="Defensive Substitution: Michael Reed replaces left fielder Keon Broxton, batting 1st, playing left field.  " des_es="Sustituci&#243;n a la Defensiva: Michael Reed reemplaza a jardinero izquierdo Keon Broxton, como primer bate y jugando en el jardinero izquierdo.  " event="Defensive Sub" event_es="Sustituci&#243;n Defensiva" tfs="213701" tfs_zulu="2016-03-13T21:37:01Z" player="605439" pitch="1" event_num="253" home_team_runs="4" away_team_runs="2"/><action b="0" s="0" o="0" des="Defensive Substitution: Nate Orf replaces third baseman Aaron Hill, batting 3rd, playing third base.  " des_es="Sustituci&#243;n a la Defensiva: Nate Orf reemplaza a tercera base Aaron Hill, como tercer bate y jugando en el tercera base.  " event="Defensive Sub" event_es="Sustituci&#243;n Defensiva" tfs="213701" tfs_zulu="2016-03-13T21:37:01Z" player="644337" pitch="1" event_num="255" home_team_runs="4" away_team_runs="2"/><action b="0" s="0" o="0" des="Defensive Substitution: Alex Presley replaces center fielder Kirk Nieuwenhuis, batting 4th, playing center field.  " des_es="Sustituci&#243;n a la Defensiva: Alex Presley reemplaza a jardinero central Kirk Nieuwenhuis, como cuarto bate y jugando en el jardinero central.  " event="Defensive Sub" event_es="Sustituci&#243;n Defensiva" tfs="213701" tfs_zulu="2016-03-13T21:37:01Z" player="502100" pitch="1" event_num="257" home_team_runs="4" away_team_runs="2"/><action b="0" s="0" o="0" des="Defensive Substitution: Shane Peterson replaces right fielder Rymer Liriano, batting 5th, playing right field.  " des_es="Sustituci&#243;n a la Defensiva: Shane Peterson reemplaza a jardinero derecho Rymer Liriano, como quinto bate y jugando en el jardinero derecho.  " event="Defensive Sub" event_es="Sustituci&#243;n Defensiva" tfs="213701" tfs_zulu="2016-03-13T21:37:01Z" player="451089" pitch="1" event_num="259" home_team_runs="4" away_team_runs="2"/><action b="0" s="0" o="0" des="Defensive Substitution: Ramon Flores replaces first baseman Andy Wilkins, batting 6th, playing first base.  " des_es="Sustituci&#243;n a la Defensiva: Ramon Flores reemplaza a primera base Andy Wilkins, como sexto bate y jugando en el primera base.  " event="Defensive Sub" event_es="Sustituci&#243;n Defensiva" tfs="213701" tfs_zulu="2016-03-13T21:37:01Z" player="570717" pitch="1" event_num="261" home_team_runs="4" away_team_runs="2"/><atbat num="45" b="0" s="0" o="1" start_tfs="213703" start_tfs_zulu="2016-03-13T21:37:03Z" end_tfs_zulu="2016-03-13T21:37:27Z" batter="596019" stand="L" b_height="5-11" pitcher="605200" p_throws="R" des="Francisco Lindor grounds out, second baseman Yadiel Rivera to first baseman Ramon Flores.  " des_es="Francisco Lindor batea rodado de out, segunda base Yadiel Rivera a primera base Ramon Flores.  " event_num="265" event="Groundout" event_es="Roletazo de Out" home_team_runs="4" away_team_runs="2"><pitch des="In play, out(s)" des_es="En juego, out(s)" id="263" type="X" code="X" tfs="213723" tfs_zulu="2016-03-13T21:37:23Z" x="109.20321584302326" y="134.30078125" event_num="263" sz_top="3.29" sz_bot="1.54"  cc="" mt=""/></atbat><atbat num="46" b="0" s="3" o="2" start_tfs="213901" start_tfs_zulu="2016-03-13T21:39:01Z" end_tfs_zulu="2016-03-13T21:39:04Z" batter="435063" stand="R" b_height="6-1" pitcher="605200" p_throws="R" des="Mike Napoli strikes out swinging.  " des_es="Mike Napoli se poncha tir&#225;ndole.  " event_num="271" event="Strikeout" event_es="Ponche" home_team_runs="4" away_team_runs="2"><pitch des="Swinging Strike" des_es="Strike tir&#225;ndole" id="267" type="S" code="S" tfs="213901" tfs_zulu="2016-03-13T21:39:01Z" x="121.47610828488372" y="136.18554687499997" event_num="267" sz_top="3.32" sz_bot="1.5"  cc="" mt=""/><pitch des="Swinging Strike" des_es="Strike tir&#225;ndole" id="268" type="S" code="S" tfs="213902" tfs_zulu="2016-03-13T21:39:02Z" x="121.47610828488372" y="136.18554687499997" event_num="268" sz_top="3.32" sz_bot="1.5"  cc="" mt=""/><pitch des="Swinging Strike" des_es="Strike tir&#225;ndole" id="269" type="S" code="S" tfs="213904" tfs_zulu="2016-03-13T21:39:04Z" x="104.82003997093025" y="133.82958984374997" event_num="269" sz_top="3.32" sz_bot="1.5"  cc="" mt=""/></atbat><atbat num="47" b="0" s="0" o="3" start_tfs="213953" start_tfs_zulu="2016-03-13T21:39:53Z" end_tfs_zulu="2016-03-13T21:39:58Z" batter="543228" stand="R" b_height="6-2" pitcher="605200" p_throws="R" des="Yan Gomes grounds out, third baseman Nate Orf to first baseman Ramon Flores.  " des_es="Yan Gomes batea rodado de out, tercera base Nate Orf a primera base Ramon Flores.  " event_num="275" event="Groundout" event_es="Roletazo de Out" home_team_runs="4" away_team_runs="2"><pitch des="In play, out(s)" des_es="En juego, out(s)" id="273" type="X" code="X" tfs="213955" tfs_zulu="2016-03-13T21:39:55Z" x="104.82003997093025" y="139.01269531249997" event_num="273" sz_top="3.16" sz_bot="1.42"  cc="" mt=""/></atbat></bottom></inning><inning num="7" away_team="mil" home_team="cle" next="Y"><top><action b="0" s="0" o="0" des="Defensive Substitution: Adam Moore replaces catcher Yan Gomes, batting 5th, playing catcher.  " des_es="Sustituci&#243;n a la Defensiva: Adam Moore reemplaza a receptor Yan Gomes, como quinto bate y jugando en el receptor.  " event="Defensive Sub" event_es="Sustituci&#243;n Defensiva" tfs="214105" tfs_zulu="2016-03-13T21:41:05Z" player="446192" pitch="1" event_num="278" home_team_runs="4" away_team_runs="2"/><atbat num="48" b="4" s="0" o="0" start_tfs="214311" start_tfs_zulu="2016-03-13T21:43:11Z" end_tfs_zulu="2016-03-13T21:43:16Z" batter="542340" stand="L" b_height="6-1" pitcher="543704" p_throws="R" des="Jonathan Villar walks.  " des_es="Jonathan Villar recibe base por bolas.  " event_num="285" event="Walk" event_es="Base por Bolas" home_team_runs="4" away_team_runs="2"><pitch des="Ball" des_es="Bola mala" id="280" type="B" code="B" tfs="214312" tfs_zulu="2016-03-13T21:43:12Z" x="99.12191133720931" y="66.92041015624999" event_num="280" sz_top="3.411" sz_bot="1.565"  cc="" mt=""/><pitch des="Ball" des_es="Bola mala" id="281" type="B" code="B" tfs="214313" tfs_zulu="2016-03-13T21:43:13Z" x="99.12191133720931" y="66.92041015624999" event_num="281" sz_top="3.411" sz_bot="1.565"  cc="" mt=""/><pitch des="Ball" des_es="Bola mala" id="282" type="B" code="B" tfs="214313" tfs_zulu="2016-03-13T21:43:13Z" x="99.12191133720931" y="66.92041015624999" event_num="282" sz_top="3.411" sz_bot="1.565"  cc="" mt=""/><pitch des="Ball" des_es="Bola mala" id="283" type="B" code="B" tfs="214315" tfs_zulu="2016-03-13T21:43:15Z" x="84.21911337209302" y="60.794921874999986" event_num="283" sz_top="3.411" sz_bot="1.565"  cc="" mt=""/><runner id="542340" start="" end="1B" event="Walk" event_num="285"/></atbat><atbat num="49" b="0" s="0" o="1" start_tfs="214452" start_tfs_zulu="2016-03-13T21:44:52Z" end_tfs_zulu="2016-03-13T21:46:11Z" batter="455117" stand="R" b_height="6-0" pitcher="543704" p_throws="R" des="Martin Maldonado flies out to left fielder Joey Butler.  " des_es="Martin Maldonado batea elevado de out a jardinero izquierdo Joey Butler.  " event_num="289" event="Flyout" event_es="Elevado de Out" home_team_runs="4" away_team_runs="2"><pitch des="In play, out(s)" des_es="En juego, out(s)" id="287" type="X" code="X" tfs="214607" tfs_zulu="2016-03-13T21:46:07Z" x="116.21629723837209" y="145.13818359375" event_num="287" on_1b="542340" sz_top="3.4" sz_bot="1.49"  cc="" mt=""/></atbat><action b="1" s="0" o="1" des="With Yadiel Rivera batting, Jonathan Villar steals (1) 2nd base.  " des_es="Con Yadiel Rivera bateando, Jonathan Villar se roba (1) la 2da base.  " event="Stolen Base 2B" event_es="Base Robada 2B" tfs="214901" tfs_zulu="2016-03-13T21:49:01Z" player="542340" pitch="1" event_num="294" home_team_runs="4" away_team_runs="2"/><atbat num="50" b="1" s="0" o="1" start_tfs="214852" start_tfs_zulu="2016-03-13T21:48:52Z" end_tfs_zulu="2016-03-13T21:49:17Z" batter="592680" stand="R" b_height="6-3" pitcher="543704" p_throws="R" des="Yadiel Rivera doubles (4) on a fly ball to center fielder Collin Cowgill.   Jonathan Villar scores.  " des_es="Yadiel Rivera pega doble (4) con elevado a jardinero central Collin Cowgill.   Jonathan Villar anota.  " event_num="300" event="Double" event_es="Doble" score="T" home_team_runs="4" away_team_runs="3"><pitch des="Ball" des_es="Bola mala" id="291" type="B" code="B" tfs="214857" tfs_zulu="2016-03-13T21:48:57Z" x="105.25835755813954" y="81.52734374999997" event_num="291" on_1b="542340" sz_top="3.54" sz_bot="1.61"  cc="" mt=""/><runner id="542340" start="1B" end="2B" event="Stolen Base 2B" event_num="294"/><pitch des="In play, run(s)" des_es="En juego, carrera(s)" id="295" type="X" code="E" tfs="214911" tfs_zulu="2016-03-13T21:49:11Z" x="102.19013444767444" y="147.02294921874997" event_num="295" on_2b="542340" sz_top="3.54" sz_bot="1.61"  cc="" mt=""/><runner id="542340" start="2B" end="" event="Double" event_num="300" score="T" rbi="T" earned="T"/><runner id="592680" start="" end="2B" event="Double" event_num="300"/></atbat><atbat num="51" b="4" s="0" o="1" start_tfs="214955" start_tfs_zulu="2016-03-13T21:49:55Z" end_tfs_zulu="2016-03-13T21:50:01Z" batter="605439" stand="R" b_height="6-0" pitcher="543704" p_throws="R" des="Michael Reed walks.  " des_es="Michael Reed recibe base por bolas.  " event_num="307" event="Walk" event_es="Base por Bolas" home_team_runs="4" away_team_runs="3"><pitch des="Ball" des_es="Bola mala" id="302" type="B" code="B" tfs="214957" tfs_zulu="2016-03-13T21:49:57Z" x="121.91442587209305" y="64.09326171874999" event_num="302" on_2b="592680" sz_top="3.5" sz_bot="1.5"  cc="" mt=""/><pitch des="Ball" des_es="Bola mala" id="303" type="B" code="B" tfs="214958" tfs_zulu="2016-03-13T21:49:58Z" x="121.91442587209305" y="64.09326171874999" event_num="303" on_2b="592680" sz_top="3.5" sz_bot="1.5"  cc="" mt=""/><pitch des="Ball" des_es="Bola mala" id="304" type="B" code="B" tfs="214958" tfs_zulu="2016-03-13T21:49:58Z" x="121.91442587209305" y="64.09326171874999" event_num="304" on_2b="592680" sz_top="3.5" sz_bot="1.5"  cc="" mt=""/><pitch des="Ball" des_es="Bola mala" id="305" type="B" code="B" tfs="215000" tfs_zulu="2016-03-13T21:50:00Z" x="121.91442587209305" y="64.09326171874999" event_num="305" on_2b="592680" sz_top="3.5" sz_bot="1.5"  cc="" mt=""/><runner id="605439" start="" end="1B" event="Walk" event_num="307"/></atbat><action b="0" s="0" o="1" des="Offensive Substitution: Pinch-hitter Colin Walsh replaces Jonathan Lucroy.  " des_es="Sustituci&#243;n a la ofensiva: bateador emergente Colin Walsh reemplaza a Jonathan Lucroy.  " event="Offensive Sub" event_es="Cambio Defensivo" tfs="215010" tfs_zulu="2016-03-13T21:50:10Z" player="595023" pitch="4" event_num="309" home_team_runs="4" away_team_runs="3"/><atbat num="52" b="4" s="0" o="1" start_tfs="215250" start_tfs_zulu="2016-03-13T21:52:50Z" end_tfs_zulu="2016-03-13T21:52:55Z" batter="595023" stand="L" b_height="6-1" pitcher="543704" p_throws="R" des="Colin Walsh walks.   Yadiel Rivera to 3rd.    Michael Reed to 2nd.  " des_es="Colin Walsh recibe base por bolas.   Yadiel Rivera a 3ra.    Michael Reed a 2da.  " event_num="318" event="Walk" event_es="Base por Bolas" home_team_runs="4" away_team_runs="3"><pitch des="Ball" des_es="Bola mala" id="311" type="B" code="B" tfs="215251" tfs_zulu="2016-03-13T21:52:51Z" x="111.39480377906979" y="78.22900390624999" event_num="311" on_1b="605439" on_2b="592680" sz_top="3.58" sz_bot="1.55"  cc="" mt=""/><pitch des="Ball" des_es="Bola mala" id="312" type="B" code="B" tfs="215251" tfs_zulu="2016-03-13T21:52:51Z" x="111.39480377906979" y="78.22900390624999" event_num="312" on_1b="605439" on_2b="592680" sz_top="3.58" sz_bot="1.55"  cc="" mt=""/><pitch des="Ball" des_es="Bola mala" id="313" type="B" code="B" tfs="215252" tfs_zulu="2016-03-13T21:52:52Z" x="111.39480377906979" y="78.22900390624999" event_num="313" on_1b="605439" on_2b="592680" sz_top="3.58" sz_bot="1.55"  cc="" mt=""/><pitch des="Ball" des_es="Bola mala" id="314" type="B" code="B" tfs="215253" tfs_zulu="2016-03-13T21:52:53Z" x="111.39480377906979" y="78.22900390624999" event_num="314" on_1b="605439" on_2b="592680" sz_top="3.58" sz_bot="1.55"  cc="" mt=""/><runner id="605439" start="1B" end="2B" event="Walk" event_num="318"/><runner id="592680" start="2B" end="3B" event="Walk" event_num="318"/><runner id="595023" start="" end="1B" event="Walk" event_num="318"/></atbat><atbat num="53" b="0" s="0" o="1" start_tfs="215536" start_tfs_zulu="2016-03-13T21:55:36Z" end_tfs_zulu="2016-03-13T21:55:54Z" batter="644337" stand="R" b_height="5-9" pitcher="543704" p_throws="R" des="Nate Orf doubles (1) on a line drive to right fielder Zach Walters.   Yadiel Rivera scores.    Michael Reed scores.    Colin Walsh to 3rd.  " des_es="Nate Orf pega doble (1) con l&#237;nea a jardinero derecho Zach Walters.   Yadiel Rivera anota  Michael Reed anota  Colin Walsh a 3ra.  " event_num="327" event="Double" event_es="Doble" score="T" home_team_runs="4" away_team_runs="5"><pitch des="In play, run(s)" des_es="En juego, carrera(s)" id="320" type="X" code="E" tfs="215540" tfs_zulu="2016-03-13T21:55:40Z" x="117.96956758720933" y="145.13818359375" event_num="320" on_1b="595023" on_2b="605439" on_3b="592680" sz_top="3.285" sz_bot="1.487"  cc="" mt=""/><runner id="595023" start="1B" end="3B" event="Double" event_num="327"/><runner id="605439" start="2B" end="" event="Double" event_num="327" score="T" rbi="T" earned="T"/><runner id="592680" start="3B" end="" event="Double" event_num="327" score="T" rbi="T" earned="T"/><runner id="644337" start="" end="2B" event="Double" event_num="327"/></atbat><action b="0" s="0" o="1" des="Pitching Change: Adam Plutko replaces Will Roberts.  " des_es="Cambio de Lanzador: Adam Plutko reemplaza a Will Roberts.  " event="Pitching Substitution" event_es="Cambio de Lanzador" tfs="215603" tfs_zulu="2016-03-13T21:56:03Z" player="592644" pitch="1" event_num="329" home_team_runs="4" away_team_runs="5"/><atbat num="54" b="4" s="0" o="1" start_tfs="220057" start_tfs_zulu="2016-03-13T22:00:57Z" end_tfs_zulu="2016-03-13T22:01:03Z" batter="502100" stand="L" b_height="5-10" pitcher="592644" p_throws="R" des="Alex Presley walks.  " des_es="Alex Presley recibe base por bolas.  " event_num="336" event="Walk" event_es="Base por Bolas" home_team_runs="4" away_team_runs="5"><pitch des="Ball" des_es="Bola mala" id="331" type="B" code="B" tfs="220058" tfs_zulu="2016-03-13T22:00:58Z" x="117.96956758720933" y="83.88330078124999" event_num="331" on_2b="644337" on_3b="595023" sz_top="3.37" sz_bot="1.58"  cc="" mt=""/><pitch des="Ball" des_es="Bola mala" id="332" type="B" code="B" tfs="220059" tfs_zulu="2016-03-13T22:00:59Z" x="117.96956758720933" y="83.88330078124999" event_num="332" on_2b="644337" on_3b="595023" sz_top="3.37" sz_bot="1.58"  cc="" mt=""/><pitch des="Ball" des_es="Bola mala" id="333" type="B" code="B" tfs="220100" tfs_zulu="2016-03-13T22:01:00Z" x="117.96956758720933" y="83.88330078124999" event_num="333" on_2b="644337" on_3b="595023" sz_top="3.37" sz_bot="1.58"  cc="" mt=""/><pitch des="Ball" des_es="Bola mala" id="334" type="B" code="B" tfs="220102" tfs_zulu="2016-03-13T22:01:02Z" x="117.96956758720933" y="83.88330078124999" event_num="334" on_2b="644337" on_3b="595023" sz_top="3.37" sz_bot="1.58"  cc="" mt=""/><runner id="502100" start="" end="1B" event="Walk" event_num="336"/></atbat><atbat num="55" b="0" s="3" o="2" start_tfs="220106" start_tfs_zulu="2016-03-13T22:01:06Z" end_tfs_zulu="2016-03-13T22:02:10Z" batter="451089" stand="L" b_height="6-0" pitcher="592644" p_throws="R" des="Shane Peterson strikes out swinging.  " des_es="Shane Peterson se poncha tir&#225;ndole.  " event_num="342" event="Strikeout" event_es="Ponche" home_team_runs="4" away_team_runs="5"><pitch des="Swinging Strike" des_es="Strike tir&#225;ndole" id="338" type="S" code="S" tfs="220207" tfs_zulu="2016-03-13T22:02:07Z" x="116.65461482558142" y="136.18554687499997" event_num="338" on_1b="502100" on_2b="644337" on_3b="595023" sz_top="3.49" sz_bot="1.5"  cc="" mt=""/><pitch des="Swinging Strike" des_es="Strike tir&#225;ndole" id="339" type="S" code="S" tfs="220207" tfs_zulu="2016-03-13T22:02:07Z" x="115.7779796511628" y="140.42626953125" event_num="339" on_1b="502100" on_2b="644337" on_3b="595023" sz_top="3.49" sz_bot="1.5"  cc="" mt=""/><pitch des="Swinging Strike" des_es="Strike tir&#225;ndole" id="340" type="S" code="S" tfs="220209" tfs_zulu="2016-03-13T22:02:09Z" x="115.7779796511628" y="140.42626953125" event_num="340" on_1b="502100" on_2b="644337" on_3b="595023" sz_top="3.49" sz_bot="1.5"  cc="" mt=""/></atbat><atbat num="56" b="0" s="3" o="3" start_tfs="220404" start_tfs_zulu="2016-03-13T22:04:04Z" end_tfs_zulu="2016-03-13T22:04:07Z" batter="570717" stand="L" b_height="5-10" pitcher="592644" p_throws="R" des="Ramon Flores strikes out swinging.  " des_es="Ramon Flores se poncha tir&#225;ndole.  " event_num="348" event="Strikeout" event_es="Ponche" home_team_runs="4" away_team_runs="5"><pitch des="Swinging Strike" des_es="Strike tir&#225;ndole" id="344" type="S" code="S" tfs="220405" tfs_zulu="2016-03-13T22:04:05Z" x="104.38172238372093" y="118.28027343749999" event_num="344" on_1b="502100" on_2b="644337" on_3b="595023" sz_top="3.62" sz_bot="1.54"  cc="" mt=""/><pitch des="Swinging Strike" des_es="Strike tir&#225;ndole" id="345" type="S" code="S" tfs="220405" tfs_zulu="2016-03-13T22:04:05Z" x="104.38172238372093" y="118.28027343749999" event_num="345" on_1b="502100" on_2b="644337" on_3b="595023" sz_top="3.62" sz_bot="1.54"  cc="" mt=""/><pitch des="Swinging Strike" des_es="Strike tir&#225;ndole" id="346" type="S" code="S" tfs="220407" tfs_zulu="2016-03-13T22:04:07Z" x="104.38172238372093" y="118.28027343749999" event_num="346" on_1b="502100" on_2b="644337" on_3b="595023" sz_top="3.62" sz_bot="1.54"  cc="" mt=""/><runner id="502100" start="1B" end="" event="Strikeout" event_num="348"/><runner id="644337" start="2B" end="" event="Strikeout" event_num="348"/><runner id="595023" start="3B" end="" event="Strikeout" event_num="348"/></atbat></top><bottom><action b="0" s="0" o="0" des="Colin Walsh remains in the game as the designated hitter.  " des_es="Colin Walsh permanece en el juego como el bateador designado.  " event="Defensive Switch" event_es="Cambio Defensivo" tfs="220803" tfs_zulu="2016-03-13T22:08:03Z" player="595023" pitch="3" event_num="352" home_team_runs="4" away_team_runs="5"/><action b="0" s="0" o="0" des="Defensive Substitution: Orlando Arcia replaces shortstop Jonathan Villar, batting 7th, playing shortstop.  " des_es="Sustituci&#243;n a la Defensiva: Orlando Arcia reemplaza a campo corto Jonathan Villar, como s&#233;ptimo bate y jugando en el campo corto.  " event="Defensive Sub" event_es="Sustituci&#243;n Defensiva" tfs="220803" tfs_zulu="2016-03-13T22:08:03Z" player="606115" pitch="3" event_num="354" home_team_runs="4" away_team_runs="5"/><action b="0" s="0" o="0" des="Defensive Substitution: Hernan Perez replaces second baseman Yadiel Rivera, batting 9th, playing second base.  " des_es="Sustituci&#243;n a la Defensiva: Hernan Perez reemplaza a segunda base Yadiel Rivera, como noveno bate y jugando en el segunda base.  " event="Defensive Sub" event_es="Sustituci&#243;n Defensiva" tfs="220803" tfs_zulu="2016-03-13T22:08:03Z" player="541650" pitch="3" event_num="356" home_team_runs="4" away_team_runs="5"/><action b="0" s="0" o="0" des="Pitching Change: Michael Blazek replaces Zach Davies.  " des_es="Cambio de Lanzador: Michael Blazek reemplaza a Zach Davies.  " event="Pitching Substitution" event_es="Cambio de Lanzador" tfs="220803" tfs_zulu="2016-03-13T22:08:03Z" player="518468" pitch="3" event_num="358" home_team_runs="4" away_team_runs="5"/><atbat num="57" b="0" s="0" o="1" start_tfs="220814" start_tfs_zulu="2016-03-13T22:08:14Z" end_tfs_zulu="2016-03-13T22:08:22Z" batter="461416" stand="L" b_height="6-3" pitcher="518468" p_throws="R" des="Will Venable grounds out, shortstop Orlando Arcia to first baseman Ramon Flores.  " des_es="Will Venable batea rodado de out, campo corto Orlando Arcia a primera base Ramon Flores.  " event_num="362" event="Groundout" event_es="Roletazo de Out" home_team_runs="4" away_team_runs="5"><pitch des="In play, out(s)" des_es="En juego, out(s)" id="360" type="X" code="X" tfs="220818" tfs_zulu="2016-03-13T22:08:18Z" x="123.22937863372096" y="137.1279296875" event_num="360" sz_top="3.62" sz_bot="1.63"  cc="" mt=""/></atbat><atbat num="58" b="0" s="0" o="2" start_tfs="220824" start_tfs_zulu="2016-03-13T22:08:24Z" end_tfs_zulu="2016-03-13T22:10:31Z" batter="518577" stand="R" b_height="5-9" pitcher="518468" p_throws="R" des="Collin Cowgill flies out to center fielder Alex Presley.  " des_es="Collin Cowgill batea elevado de out a jardinero central Alex Presley.  " event_num="366" event="Flyout" event_es="Elevado de Out" home_team_runs="4" away_team_runs="5"><pitch des="In play, out(s)" des_es="En juego, out(s)" id="364" type="X" code="X" tfs="221024" tfs_zulu="2016-03-13T22:10:24Z" x="120.59947311046514" y="143.25341796875" event_num="364" sz_top="3.13" sz_bot="1.44"  cc="" mt=""/></atbat><atbat num="59" b="0" s="0" o="3" start_tfs="221036" start_tfs_zulu="2016-03-13T22:10:36Z" end_tfs_zulu="2016-03-13T22:10:41Z" batter="542994" stand="R" b_height="6-2" pitcher="518468" p_throws="R" des="Joey Butler grounds out, shortstop Orlando Arcia to first baseman Ramon Flores.  " des_es="Joey Butler batea rodado de out, campo corto Orlando Arcia a primera base Ramon Flores.  " event_num="370" event="Groundout" event_es="Roletazo de Out" home_team_runs="4" away_team_runs="5"><pitch des="In play, out(s)" des_es="En juego, out(s)" id="368" type="X" code="X" tfs="221037" tfs_zulu="2016-03-13T22:10:37Z" x="113.58639171511628" y="129.11767578125" event_num="368" sz_top="3.54" sz_bot="1.72"  cc="" mt=""/></atbat></bottom></inning><inning num="8" away_team="mil" home_team="cle" next="Y"><top><action b="0" s="0" o="0" des="Defensive Substitution: Jeremy Lucas replaces first baseman Mike Napoli, batting 4th, playing first base.  " des_es="Sustituci&#243;n a la Defensiva: Jeremy Lucas reemplaza a primera base Mike Napoli, como cuarto bate y jugando en el primera base.  " event="Defensive Sub" event_es="Sustituci&#243;n Defensiva" tfs="221212" tfs_zulu="2016-03-13T22:12:12Z" player="572997" pitch="1" event_num="373" home_team_runs="4" away_team_runs="5"/><action b="0" s="0" o="0" des="Defensive Substitution: Shane Robinson replaces center fielder Collin Cowgill, batting 7th, playing center field.  " des_es="Sustituci&#243;n a la Defensiva: Shane Robinson reemplaza a jardinero central Collin Cowgill, como s&#233;ptimo bate y jugando en el jardinero central.  " event="Defensive Sub" event_es="Sustituci&#243;n Defensiva" tfs="221212" tfs_zulu="2016-03-13T22:12:12Z" player="453203" pitch="1" event_num="375" home_team_runs="4" away_team_runs="5"/><action b="0" s="0" o="0" des="Defensive Substitution: James Ramsey replaces left fielder Joey Butler, batting 8th, playing left field.  " des_es="Sustituci&#243;n a la Defensiva: James Ramsey reemplaza a jardinero izquierdo Joey Butler, como octavo bate y jugando en el  jardinero izquierdo.  " event="Defensive Sub" event_es="Sustituci&#243;n Defensiva" tfs="221212" tfs_zulu="2016-03-13T22:12:12Z" player="607256" pitch="1" event_num="377" home_team_runs="4" away_team_runs="5"/><atbat num="60" b="0" s="0" o="1" start_tfs="221318" start_tfs_zulu="2016-03-13T22:13:18Z" end_tfs_zulu="2016-03-13T22:13:25Z" batter="606115" stand="R" b_height="6-0" pitcher="592644" p_throws="R" des="Orlando Arcia flies out to right fielder Zach Walters.  " des_es="Orlando Arcia batea elevado de out a jardinero derecho Zach Walters.  " event_num="381" event="Flyout" event_es="Elevado de Out" home_team_runs="4" away_team_runs="5"><pitch des="In play, out(s)" des_es="En juego, out(s)" id="379" type="X" code="X" tfs="221322" tfs_zulu="2016-03-13T22:13:22Z" x="107.01162790697674" y="133.82958984374997" event_num="379" sz_top="3.45" sz_bot="1.5"  cc="" mt=""/></atbat><action b="0" s="0" o="1" des="Offensive Substitution: Pinch-hitter Jacob Nottingham replaces Martin Maldonado.  " des_es="Sustituci&#243;n a la ofensiva: bateador emergente Jacob Nottingham reemplaza a Martin Maldonado.  " event="Offensive Sub" event_es="Cambio Defensivo" tfs="221331" tfs_zulu="2016-03-13T22:13:31Z" player="641924" pitch="1" event_num="383" home_team_runs="4" away_team_runs="5"/><atbat num="61" b="0" s="3" o="2" start_tfs="221456" start_tfs_zulu="2016-03-13T22:14:56Z" end_tfs_zulu="2016-03-13T22:14:59Z" batter="641924" stand="R" b_height="6-2" pitcher="592644" p_throws="R" des="Jacob Nottingham strikes out swinging.  " des_es="Jacob Nottingham se poncha tir&#225;ndole.  " event_num="389" event="Strikeout" event_es="Ponche" home_team_runs="4" away_team_runs="5"><pitch des="Swinging Strike" des_es="Strike tir&#225;ndole" id="385" type="S" code="S" tfs="221457" tfs_zulu="2016-03-13T22:14:57Z" x="96.93032340116281" y="134.30078125" event_num="385" sz_top="3.467" sz_bot="1.589"  cc="" mt=""/><pitch des="Swinging Strike" des_es="Strike tir&#225;ndole" id="386" type="S" code="S" tfs="221458" tfs_zulu="2016-03-13T22:14:58Z" x="96.93032340116281" y="134.30078125" event_num="386" sz_top="3.467" sz_bot="1.589"  cc="" mt=""/><pitch des="Swinging Strike" des_es="Strike tir&#225;ndole" id="387" type="S" code="S" tfs="221459" tfs_zulu="2016-03-13T22:14:59Z" x="96.93032340116281" y="134.30078125" event_num="387" sz_top="3.467" sz_bot="1.589"  cc="" mt=""/></atbat><atbat num="62" b="0" s="0" o="3" start_tfs="221500" start_tfs_zulu="2016-03-13T22:15:00Z" end_tfs_zulu="2016-03-13T22:16:24Z" batter="541650" stand="R" b_height="6-1" pitcher="592644" p_throws="R" des="Hernan Perez flies out to left fielder James Ramsey.  " des_es="Hernan Perez batea elevado de out a jardinero izquierdo James Ramsey.  " event_num="393" event="Flyout" event_es="Elevado de Out" home_team_runs="4" away_team_runs="5"><pitch des="In play, out(s)" des_es="En juego, out(s)" id="391" type="X" code="X" tfs="221621" tfs_zulu="2016-03-13T22:16:21Z" x="121.47610828488372" y="139.01269531249997" event_num="391" sz_top="3.52" sz_bot="1.53"  cc="" mt=""/></atbat></top><bottom><action b="0" s="0" o="0" des="Jacob Nottingham remains in the game as the catcher.  " des_es="Jacob Nottingham permanece en el juego como el receptor.  " event="Defensive Switch" event_es="Cambio Defensivo" tfs="221721" tfs_zulu="2016-03-13T22:17:21Z" player="641924" pitch="1" event_num="396" home_team_runs="4" away_team_runs="5"/><action b="0" s="0" o="0" des="Pitching Change: Blaine Boyer replaces Michael Blazek.  " des_es="Cambio de Lanzador: Blaine Boyer reemplaza a Michael Blazek.  " event="Pitching Substitution" event_es="Cambio de Lanzador" tfs="221721" tfs_zulu="2016-03-13T22:17:21Z" player="430641" pitch="1" event_num="398" home_team_runs="4" away_team_runs="5"/><atbat num="63" b="0" s="0" o="1" start_tfs="222000" start_tfs_zulu="2016-03-13T22:20:00Z" end_tfs_zulu="2016-03-13T22:20:13Z" batter="492841" stand="L" b_height="5-9" pitcher="430641" p_throws="R" des="Michael Martinez grounds out, second baseman Hernan Perez to first baseman Ramon Flores.  " des_es="Michael Martinez batea rodado de out, segunda base Hernan Perez a primera base Ramon Flores.  " event_num="402" event="Groundout" event_es="Roletazo de Out" home_team_runs="4" away_team_runs="5"><pitch des="In play, out(s)" des_es="En juego, out(s)" id="400" type="X" code="X" tfs="222004" tfs_zulu="2016-03-13T22:20:04Z" x="112.7097565406977" y="149.85009765624997" event_num="400" sz_top="3.21" sz_bot="1.51"  cc="" mt=""/></atbat><atbat num="64" b="0" s="0" o="2" start_tfs="222114" start_tfs_zulu="2016-03-13T22:21:14Z" end_tfs_zulu="2016-03-13T22:21:19Z" batter="595025" stand="L" b_height="6-2" pitcher="430641" p_throws="R" des="Zach Walters grounds out to first baseman Ramon Flores.  " des_es="Zach Walters batea rodado de out a primera base Ramon Flores.  " event_num="406" event="Groundout" event_es="Roletazo de Out" home_team_runs="4" away_team_runs="5"><pitch des="In play, out(s)" des_es="En juego, out(s)" id="404" type="X" code="X" tfs="222115" tfs_zulu="2016-03-13T22:21:15Z" x="116.65461482558142" y="148.4365234375" event_num="404" sz_top="3.467" sz_bot="1.589"  cc="" mt=""/></atbat><atbat num="65" b="0" s="0" o="3" start_tfs="222310" start_tfs_zulu="2016-03-13T22:23:10Z" end_tfs_zulu="2016-03-13T22:23:15Z" batter="543401" stand="L" b_height="5-11" pitcher="430641" p_throws="R" des="Jason Kipnis flies out to center fielder Alex Presley.  " des_es="Jason Kipnis batea elevado de out a jardinero central Alex Presley.  " event_num="410" event="Flyout" event_es="Elevado de Out" home_team_runs="4" away_team_runs="5"><pitch des="In play, out(s)" des_es="En juego, out(s)" id="408" type="X" code="X" tfs="222312" tfs_zulu="2016-03-13T22:23:12Z" x="110.95648619186046" y="153.61962890625" event_num="408" sz_top="3.26" sz_bot="1.48"  cc="" mt=""/></atbat></bottom></inning><inning num="9" away_team="mil" home_team="cle" next="N"><top><action b="0" s="0" o="0" des="Defensive Substitution: Todd Hankins replaces second baseman Jason Kipnis, batting 2nd, playing second base.  " des_es="Sustituci&#243;n a la Defensiva: Todd Hankins reemplaza a segunda base Jason Kipnis, como segundo bate y jugando en el  segunda base.  " event="Defensive Sub" event_es="Sustituci&#243;n Defensiva" tfs="222527" tfs_zulu="2016-03-13T22:25:27Z" player="607399" pitch="1" event_num="413" home_team_runs="4" away_team_runs="5"/><action b="0" s="0" o="0" des="Defensive Substitution: Ronny Rodriguez replaces third baseman Michael Martinez, batting 9th, playing third base.  " des_es="Sustituci&#243;n a la Defensiva: Ronny Rodriguez reemplaza a tercera base Michael Martinez, como noveno bate y jugando en el tercera base.  " event="Defensive Sub" event_es="Sustituci&#243;n Defensiva" tfs="222527" tfs_zulu="2016-03-13T22:25:27Z" player="500135" pitch="1" event_num="415" home_team_runs="4" away_team_runs="5"/><action b="0" s="0" o="0" des="Pitching Change: Jarrett Grube replaces Adam Plutko.  " des_es="Cambio de Lanzador: Jarrett Grube reemplaza a Adam Plutko.  " event="Pitching Substitution" event_es="Cambio de Lanzador" tfs="222527" tfs_zulu="2016-03-13T22:25:27Z" player="459439" pitch="1" event_num="417" home_team_runs="4" away_team_runs="5"/><atbat num="66" b="0" s="0" o="0" start_tfs="222750" start_tfs_zulu="2016-03-13T22:27:50Z" end_tfs_zulu="2016-03-13T22:28:41Z" batter="605439" stand="R" b_height="6-0" pitcher="459439" p_throws="R" des="Michael Reed singles on a line drive to left fielder James Ramsey.  " des_es="Michael Reed pega sencillo con l&#237;nea a jardinero izquierdo James Ramsey.  " event_num="421" event="Single" event_es="Sencillo" home_team_runs="4" away_team_runs="5"><pitch des="In play, no out" des_es="En juego, no out" id="419" type="X" code="D" tfs="222836" tfs_zulu="2016-03-13T22:28:36Z" x="120.16115552325581" y="154.56201171875" event_num="419" sz_top="3.5" sz_bot="1.5"  cc="" mt=""/><runner id="605439" start="" end="1B" event="Single" event_num="421"/></atbat><atbat num="67" b="0" s="0" o="1" start_tfs="222846" start_tfs_zulu="2016-03-13T22:28:46Z" end_tfs_zulu="2016-03-13T22:28:56Z" batter="595023" stand="L" b_height="6-1" pitcher="459439" p_throws="R" des="Colin Walsh flies out to left fielder James Ramsey.  " des_es="Colin Walsh batea elevado de out a jardinero izquierdo James Ramsey.  " event_num="425" event="Flyout" event_es="Elevado de Out" home_team_runs="4" away_team_runs="5"><pitch des="In play, out(s)" des_es="En juego, out(s)" id="423" type="X" code="X" tfs="222852" tfs_zulu="2016-03-13T22:28:52Z" x="112.27143895348837" y="142.31103515625" event_num="423" on_1b="605439" sz_top="3.58" sz_bot="1.55"  cc="" mt=""/></atbat><action b="1" s="0" o="1" des="With Nate Orf batting, Michael Reed steals (1) 2nd base.  " des_es="Con Nate Orf bateando, Michael Reed se roba (1) la 2da base.  " event="Stolen Base 2B" event_es="Base Robada 2B" tfs="222910" tfs_zulu="2016-03-13T22:29:10Z" player="605439" pitch="1" event_num="430" home_team_runs="4" away_team_runs="5"/><atbat num="68" b="1" s="3" o="2" start_tfs="222859" start_tfs_zulu="2016-03-13T22:28:59Z" end_tfs_zulu="2016-03-13T22:31:31Z" batter="644337" stand="R" b_height="5-9" pitcher="459439" p_throws="R" des="Nate Orf strikes out swinging.  " des_es="Nate Orf se poncha tir&#225;ndole.  " event_num="435" event="Strikeout" event_es="Ponche" home_team_runs="4" away_team_runs="5"><pitch des="Ball" des_es="Bola mala" id="427" type="B" code="B" tfs="222902" tfs_zulu="2016-03-13T22:29:02Z" x="114.0247093023256" y="83.41210937499999" event_num="427" on_1b="605439" sz_top="3.285" sz_bot="1.487"  cc="" mt=""/><runner id="605439" start="1B" end="2B" event="Stolen Base 2B" event_num="430"/><pitch des="Swinging Strike" des_es="Strike tir&#225;ndole" id="431" type="S" code="S" tfs="223126" tfs_zulu="2016-03-13T22:31:26Z" x="114.46302688953489" y="152.20605468749997" event_num="431" on_2b="605439" sz_top="3.285" sz_bot="1.487"  cc="" mt=""/><pitch des="Swinging Strike" des_es="Strike tir&#225;ndole" id="432" type="S" code="S" tfs="223127" tfs_zulu="2016-03-13T22:31:27Z" x="108.76489825581397" y="155.03320312499997" event_num="432" on_2b="605439" sz_top="3.285" sz_bot="1.487"  cc="" mt=""/><pitch des="Swinging Strike" des_es="Strike tir&#225;ndole" id="433" type="S" code="S" tfs="223129" tfs_zulu="2016-03-13T22:31:29Z" x="109.64153343023256" y="155.03320312499997" event_num="433" on_2b="605439" sz_top="3.285" sz_bot="1.487"  cc="" mt=""/></atbat><atbat num="69" b="0" s="0" o="3" start_tfs="223222" start_tfs_zulu="2016-03-13T22:32:22Z" end_tfs_zulu="2016-03-13T22:32:30Z" batter="502100" stand="L" b_height="5-10" pitcher="459439" p_throws="R" des="Alex Presley flies out to left fielder James Ramsey.  " des_es="Alex Presley batea elevado de out a jardinero izquierdo James Ramsey.  " event_num="439" event="Flyout" event_es="Elevado de Out" home_team_runs="4" away_team_runs="5"><pitch des="In play, out(s)" des_es="En juego, out(s)" id="437" type="X" code="X" tfs="223226" tfs_zulu="2016-03-13T22:32:26Z" x="108.76489825581397" y="155.50439453124997" event_num="437" on_2b="605439" sz_top="3.37" sz_bot="1.58"  cc="" mt=""/><runner id="605439" start="2B" end="" event="Flyout" event_num="439"/></atbat></top><bottom><action b="0" s="0" o="0" des="Pitching Change: Jorge Lopez replaces Blaine Boyer.  " des_es="Cambio de Lanzador: Jorge Lopez reemplaza a Blaine Boyer.  " event="Pitching Substitution" event_es="Cambio de Lanzador" tfs="223310" tfs_zulu="2016-03-13T22:33:10Z" player="605347" pitch="1" event_num="443" home_team_runs="4" away_team_runs="5"/><atbat num="70" b="0" s="0" o="1" start_tfs="223533" start_tfs_zulu="2016-03-13T22:35:33Z" end_tfs_zulu="2016-03-13T22:35:38Z" batter="596019" stand="L" b_height="5-11" pitcher="605347" p_throws="R" des="Francisco Lindor flies out to left fielder Michael Reed.  " des_es="Francisco Lindor batea elevado de out a jardinero izquierdo Michael Reed.  " event_num="447" event="Flyout" event_es="Elevado de Out" home_team_runs="4" away_team_runs="5"><pitch des="In play, out(s)" des_es="En juego, out(s)" id="445" type="X" code="X" tfs="223534" tfs_zulu="2016-03-13T22:35:34Z" x="117.96956758720933" y="113.56835937499999" event_num="445" sz_top="3.29" sz_bot="1.54"  cc="" mt=""/></atbat><atbat num="71" b="0" s="3" o="2" start_tfs="223539" start_tfs_zulu="2016-03-13T22:35:39Z" end_tfs_zulu="2016-03-13T22:37:39Z" batter="572997" stand="R" b_height="6-1" pitcher="605347" p_throws="R" des="Jeremy Lucas strikes out swinging.  " des_es="Jeremy Lucas se poncha tir&#225;ndole.  " event_num="453" event="Strikeout" event_es="Ponche" home_team_runs="4" away_team_runs="5"><pitch des="Swinging Strike" des_es="Strike tir&#225;ndole" id="449" type="S" code="S" tfs="223736" tfs_zulu="2016-03-13T22:37:36Z" x="95.6153706395349" y="142.31103515625" event_num="449" sz_top="3.37" sz_bot="1.52"  cc="" mt=""/><pitch des="Swinging Strike" des_es="Strike tir&#225;ndole" id="450" type="S" code="S" tfs="223737" tfs_zulu="2016-03-13T22:37:37Z" x="94.300417877907" y="141.83984374999997" event_num="450" sz_top="3.37" sz_bot="1.52"  cc="" mt=""/><pitch des="Swinging Strike" des_es="Strike tir&#225;ndole" id="451" type="S" code="S" tfs="223739" tfs_zulu="2016-03-13T22:37:39Z" x="94.300417877907" y="141.83984374999997" event_num="451" sz_top="3.37" sz_bot="1.52"  cc="" mt=""/></atbat><atbat num="72" b="0" s="0" o="2" start_tfs="223947" start_tfs_zulu="2016-03-13T22:39:47Z" end_tfs_zulu="2016-03-13T22:39:54Z" batter="446192" stand="R" b_height="6-3" pitcher="605347" p_throws="R" des="Adam Moore singles on a ground ball to center fielder Alex Presley.  " des_es="Adam Moore pega sencillo con rodado a jardinero central Alex Presley.  " event_num="457" event="Single" event_es="Sencillo" home_team_runs="4" away_team_runs="5"><pitch des="In play, no out" des_es="En juego, no out" id="455" type="X" code="D" tfs="223949" tfs_zulu="2016-03-13T22:39:49Z" x="110.95648619186046" y="144.19580078124997" event_num="455" sz_top="3.49" sz_bot="1.601"  cc="" mt=""/><runner id="446192" start="" end="1B" event="Single" event_num="457"/></atbat><action b="0" s="0" o="2" des="Offensive Substitution: Pinch-hitter Mike Papi replaces Will Venable.  " des_es="Sustituci&#243;n a la ofensiva: bateador emergente Mike Papi reemplaza a Will Venable.  " event="Offensive Sub" event_es="Cambio Defensivo" tfs="224048" tfs_zulu="2016-03-13T22:40:48Z" player="596068" pitch="1" event_num="459" home_team_runs="4" away_team_runs="5"/><action b="0" s="0" o="2" des="Offensive Substitution: Pinch-runner Erik Gonzalez replaces Adam Moore.  " des_es="Sustituci&#243;n a la ofensiva: corredor emergente Erik Gonzalez reemplaza a replaces Adam Moore.  " event="Offensive Sub" event_es="Cambio Defensivo" tfs="224106" tfs_zulu="2016-03-13T22:41:06Z" player="570481" pitch="1" event_num="461" home_team_runs="4" away_team_runs="5"/><atbat num="73" b="0" s="3" o="3" start_tfs="224254" start_tfs_zulu="2016-03-13T22:42:54Z" end_tfs_zulu="2016-03-13T22:43:04Z" batter="596068" stand="L" b_height="6-3" pitcher="605347" p_throws="R" des="Mike Papi strikes out swinging.  " des_es="Mike Papi se poncha tir&#225;ndole.  " event_num="467" event="Strikeout" event_es="Ponche" home_team_runs="4" away_team_runs="5"><pitch des="Swinging Strike" des_es="Strike tir&#225;ndole" id="463" type="S" code="S" tfs="224301" tfs_zulu="2016-03-13T22:43:01Z" x="103.50508720930235" y="138.54150390624997" event_num="463" on_1b="570481" sz_top="3.47" sz_bot="1.59"  cc="" mt=""/><pitch des="Swinging Strike" des_es="Strike tir&#225;ndole" id="464" type="S" code="S" tfs="224302" tfs_zulu="2016-03-13T22:43:02Z" x="106.57331031976744" y="145.609375" event_num="464" on_1b="570481" sz_top="3.47" sz_bot="1.59"  cc="" mt=""/><pitch des="Swinging Strike" des_es="Strike tir&#225;ndole" id="465" type="S" code="S" tfs="224304" tfs_zulu="2016-03-13T22:43:04Z" x="106.57331031976744" y="145.609375" event_num="465" on_1b="570481" sz_top="3.47" sz_bot="1.59"  cc="" mt=""/><runner id="570481" start="1B" end="" event="Strikeout" event_num="467"/></atbat></bottom></inning></game>